Workbook
Name PROV_AIR_E_S_A_S__E_S_P_: LISTAS!$B$3:$B$3
Name PROV_ASTURIAS_SOLUCIONES_DE_INGENIERIA_BUCEO_COMERCIAL_Y_DRAGADO_SAS: LISTAS!$C$3:$C$4
Name PROV_CASALIMPIA_SA: LISTAS!$D$3:$D$4
Name PROV_CLARO_S_A_: LISTAS!$E$3:$E$10
Name PROV_COMPANIA_PAPELERA_NACIONAL_S_A_S: LISTAS!$F$3:$F$4
Name PROV_COMPUASOCIADOS: LISTAS!$G$3:$G$3
Name PROV_CONTRATOS_Y_FIANZAS_DE_ARRENDAMIENTO_S_A_S_: LISTAS!$H$3:$H$3
Name PROV_COORSERPARK: LISTAS!$I$3:$I$3
Name PROV_EDIFICIO_CAPITAL_TOWERS_PROPIEDAD_HORIZONTAL: LISTAS!$J$3:$J$5
Name PROV_EDIFICIO_PORTUS_MANGA_CARTAGENA: LISTAS!$K$3:$K$5
Name PROV_EDIFICIO_TORRES_DEL_ATLANTICO: LISTAS!$L$3:$L$3
Name PROV_EMERMEDICA_S_A_: LISTAS!$M$3:$M$4
Name PROV_EMPRESAS_MUNICIPALES_DE_CALI: LISTAS!$N$3:$N$3
Name PROV_EMPRESAS_PUBLICAS_DE_MEDELLIN_E_S_P: LISTAS!$O$3:$O$3
Name PROV_ETB_S_A__E_S_P: LISTAS!$P$3:$P$3
Name PROV_FEDERACION_COLOMBIANA_AGENTES_LOGISTICOS: LISTAS!$Q$3:$Q$5
Name PROV_FUNDACION_UN_TECHO_PARA_MI_PAIS_COLOMBIA: LISTAS!$R$3:$R$3
Name PROV_HARDSOFT_SOLUTIONS_INTEGRAL_SAS: LISTAS!$S$3:$S$3
Name PROV_IFX_NETWORKS_COLOMBIA_S_A_S_: LISTAS!$T$3:$T$4
Name PROV_INTERASEO_AEROPUERTO: LISTAS!$U$3:$U$3
Name PROV_INVERSIONES_HOTELERAS_BUENAVENTURA_S_A_S_: LISTAS!$V$3:$V$3
Name PROV_JAVIER_ANTONIO_SANCHEZ_O_: LISTAS!$W$3:$W$3
Name PROV_JCO_INVERSIONES_S_A_S: LISTAS!$X$3:$X$3
Name PROV_KEY_WAY_BUSINESS_CONSULTING_SAS: LISTAS!$Y$3:$Y$3
Name PROV_LI_STORAGE_SAS: LISTAS!$Z$3:$Z$3
Name PROV_LUZ_DARY_MINA_GARCES: LISTAS!$AA$3:$AA$3
Name PROV_MARVAL_S_A_S_: LISTAS!$AB$3:$AB$3
Name PROV_MEDISANITAS_S_A_S_: LISTAS!$AC$3:$AC$3
Name PROV_MOVISTAR: LISTAS!$AD$3:$AD$5
Name PROV_MULTICOPY_JV_ZOMAC_SAS: LISTAS!$AE$3:$AE$3
Name PROV_OPAIN_SA_AEROPUERTO_EL_DORADO: LISTAS!$AF$3:$AF$3
Name PROV_PALAN_SOCIEDAD_POR_ACCIONES_SIMPLIFICADA: LISTAS!$AG$3:$AG$3
Name PROV_PATRIMONIOS_AUTONOMOS_FIDUCIARIA_BANCOLOMBIA_S_A: LISTAS!$AH$3:$AH$4
Name PROV_PORTUS_GLOBAL_SAS: LISTAS!$AI$3:$AI$3
Name PROV_PRUEBA: LISTAS!$AQ$3:$AQ$4
Name PROV_SERVIDOMESTICAS_SAS: LISTAS!$AJ$3:$AJ$3
Name PROV_SUMAR_INVERSIONES_Y_PROYECTOS_S_A_S_: LISTAS!$AK$3:$AK$3
Name PROV_TECNOLOGIA_INFORMATICA_TECINF_SAS: LISTAS!$AL$3:$AL$3
Name PROV_TRAIKER_GROUP_COLOMBIA_S_A_S_: LISTAS!$AM$3:$AM$3
Name PROV_TRANS_INTERNATIONAL_COURIER_S_A_S: LISTAS!$AN$3:$AN$3
Name PROV_TRIPLE_A: LISTAS!$AO$3:$AO$3
Name PROV_UNE_EPM_TELECOMUNICACIONES_S_A: LISTAS!$AP$3:$AP$5
Name PROVEEDORES: LISTAS!$A$3:$A$44

Sheet MAESTRA
A1: BASE MAESTRA DE HOMOLOGACIÓN — CRAFT | No editar directamente
A2: CLAVE (no editar) | B2: NIT | C2: PROVEEDOR | D2: SERVICIO | E2: ÁREA | F2: P&L | G2: CUENTA CONTABLE | H2: GLOSA ESTÁNDAR | I2: TIPO | J2: SUCURSAL
A3: EDIFICIO CAPITAL TOWERS PROPIEDAD HORIZONTAL|||Arriendo bodega | B3: 830082820-5 | C3: EDIFICIO CAPITAL TOWERS PROPIEDAD HORIZONTAL | D3: Arriendo bodega | E3: ADM | F3: CONSTRUCCIONES Y EDIFICACIONES | G3: CONSTRUCCIONES Y EDIFICACIONES | H3: ARRIENDO BODEGA OF BOG | I3: Fijo | J3: Calle 100
A4: EDIFICIO CAPITAL TOWERS PROPIEDAD HORIZONTAL|||Administración oficina | B4: 830082820-5 | C4: EDIFICIO CAPITAL TOWERS PROPIEDAD HORIZONTAL | D4: Administración oficina | E4: ADM | F4: CONSTRUCCIONES Y EDIFICACIONES | G4: ADMINISTRACIÓN OFICINA | H4: /SERV ADMINISTRACIÓN OF/ BOG | I4: Fijo | J4: Calle 100
A5: EDIFICIO CAPITAL TOWERS PROPIEDAD HORIZONTAL|||Servicios públicos | B5: 830082820-5 | C5: EDIFICIO CAPITAL TOWERS PROPIEDAD HORIZONTAL | D5: Servicios públicos | E5: ADM | F5: ENERGIA ELECTRICA - ACUEDUCTO Y ALCANTARILLADO | G5: ENERGIA ELECTRICA - ACUEDUCTO Y ALCANTARILLADO | H5: SERVICIOS PUBLICOS OF BOG | I5: Fijo | J5: Calle 100
A6: PALAN SOCIEDAD POR ACCIONES SIMPLIFICADA|||Canon arriendo oficina | B6: 830111934-1 | C6: PALAN SOCIEDAD POR ACCIONES SIMPLIFICADA | D6: Canon arriendo oficina | E6: ADM | F6: CONSTRUCCIONES Y EDIFICACIONES | G6: CONSTRUCCIONES Y EDIFICACIONES | H6: CANON ARRIENDO OF BOG | I6: Fijo | J6: Calle 100
A7: PATRIMONIOS AUTONOMOS FIDUCIARIA BANCOLOMBIA S A|||Canon arriendo aeropuerto | B7: 830054539-0 | C7: PATRIMONIOS AUTONOMOS FIDUCIARIA BANCOLOMBIA S A | D7: Canon arriendo aeropuerto | E7: ADM | F7: CONSTRUCCIONES Y EDIFICACIONES | G7: CONSTRUCCIONES Y EDIFICACIONES | H7: CANON ARRIENDO OF AERPTO | I7: Fijo | J7: Aeropuerto
A8: PATRIMONIOS AUTONOMOS FIDUCIARIA BANCOLOMBIA S A|||Servicios públicos aeropuerto | B8: 830054539-0 | C8: PATRIMONIOS AUTONOMOS FIDUCIARIA BANCOLOMBIA S A | D8: Servicios públicos aeropuerto | E8: ADM | F8: ENERGIA ELECTRICA | G8: ENERGIA ELECTRICA | H8: SERVICIOS PUBLICOS OF AERPTO | I8: Fijo | J8: Aeropuerto
A9: LI STORAGE SAS|||Arriendo bodega externa | B9: 900705369-3 | C9: LI STORAGE SAS | D9: Arriendo bodega externa | E9: ADM | F9: CONSTRUCCIONES Y EDIFICACIONES | G9: CONSTRUCCIONES Y EDIFICACIONES | H9: ARRIENDO BODEGA EXTERNA OF BOG | I9: Fijo | J9: Calle 100
A10: ASTURIAS SOLUCIONES DE INGENIERIA BUCEO COMERCIAL Y DRAGADO SAS|||Canon arriendo oficina BUN | B10: 900081790-1 | C10: ASTURIAS SOLUCIONES DE INGENIERIA BUCEO COMERCIAL Y DRAGADO SAS | D10: Canon arriendo oficina BUN | E10: ADM | F10: CONSTRUCCIONES Y EDIFICACIONES | G10: CONSTRUCCIONES Y EDIFICACIONES | H10: CANON ARRIENDO OF BUN | I10: Fijo | J10: Buenaventura
A11: ASTURIAS SOLUCIONES DE INGENIERIA BUCEO COMERCIAL Y DRAGADO SAS|||Administración oficina BUN | B11: 900081790-1 | C11: ASTURIAS SOLUCIONES DE INGENIERIA BUCEO COMERCIAL Y DRAGADO SAS | D11: Administración oficina BUN | E11: ADM | F11: CONSTRUCCIONES Y EDIFICACIONES | G11: ADMINISTRACIÓN OFICINA | H11: /SERV ADMINISTRACIÓN OFC/ BUN | I11: Fijo | J11: Buenaventura
A12: JAVIER ANTONIO SANCHEZ O.|||Arriendo bodega BUN | B12: 1111750598-3 | C12: JAVIER ANTONIO SANCHEZ O. | D12: Arriendo bodega BUN | E12: ADM | F12: CONSTRUCCIONES Y EDIFICACIONES | G12: CONSTRUCCIONES Y EDIFICACIONES | H12: ARRIENDO BODEGA OF BUN | I12: Fijo | J12: Buenaventura
A13: PORTUS GLOBAL SAS|||Canon arriendo oficina CTG | B13: 900918697-9 | C13: PORTUS GLOBAL SAS | D13: Canon arriendo oficina CTG | E13: ADM | F13: CONSTRUCCIONES Y EDIFICACIONES | G13: CONSTRUCCIONES Y EDIFICACIONES | H13: CANON ARRIENDO OF CTG | I13: Fijo | J13: Cartagena
... A68: PRUEBA|||SERV2 | B68: 002 | C68: PRUEBA | D68: SERV2 | E68: adm | F68: cuota | G68: cuota | H68: cuota | I68: cuota | J68: cuota

Sheet LISTAS
A1: Hoja técnica — rangos para listas desplegables encadenadas
A2: PROVEEDORES | B2: AIR-E S.A.S. E.S.P. | C2: ASTURIAS SOLUCIONES DE INGENIERIA BUCEO COMERCIAL Y DRAGADO SAS | D2: CASALIMPIA SA | E2: CLARO S.A. | F2: COMPAÑIA PAPELERA NACIONAL S.A.S | G2: COMPUASOCIADOS | H2: CONTRATOS Y FIANZAS DE ARRENDAMIENTO S.A.S. | I2: COORSERPARK | J2: EDIFICIO CAPITAL TOWERS PROPIEDAD HORIZONTAL | K2: EDIFICIO PORTUS MANGA CARTAGENA | L2: EDIFICIO TORRES DEL ATLANTICO | M2: EMERMEDICA S.A. | N2: EMPRESAS MUNICIPALES DE CALI | O2: EMPRESAS PÚBLICAS DE MEDELLÍN E.S.P | P2: ETB S.A. E.S.P | Q2: FEDERACION COLOMBIANA AGENTES LOGISTICOS | R2: FUNDACION UN TECHO PARA MI PAIS COLOMBIA | S2: HARDSOFT SOLUTIONS INTEGRAL SAS | T2: IFX NETWORKS COLOMBIA S.A.S. | U2: INTERASEO AEROPUERTO | V2: INVERSIONES HOTELERAS BUENAVENTURA S.A.S. | W2: JAVIER ANTONIO SANCHEZ O. | X2: JCO INVERSIONES S.A.S | Y2: KEY WAY BUSINESS CONSULTING SAS | Z2: LI STORAGE SAS | AA2: LUZ DARY MINA GARCES | AB2: MARVAL S.A.S. | AC2: MEDISANITAS S.A.S. | AD2: MOVISTAR | AE2: MULTICOPY JV ZOMAC SAS | AF2: OPAIN SA AEROPUERTO EL DORADO | AG2: PALAN SOCIEDAD POR ACCIONES SIMPLIFICADA | AH2: PATRIMONIOS AUTONOMOS FIDUCIARIA BANCOLOMBIA S A | AI2: PORTUS GLOBAL SAS | AJ2: SERVIDOMESTICAS SAS | AK2: SUMAR INVERSIONES Y PROYECTOS S.A.S. | AL2: TECNOLOGIA INFORMATICA TECINF SAS | AM2: TRAIKER GROUP COLOMBIA S.A.S. | AN2: TRANS INTERNATIONAL COURIER S.A.S | AO2: TRIPLE A | AP2: UNE EPM TELECOMUNICACIONES S-A | AQ2: PRUEBA
A3: AIR-E S.A.S. E.S.P. | B3: Energía BRQ | C3: Canon arriendo oficina BUN | D3: Aseo oficina CTG | E3: SIM tablet BUN y aeropuerto | F3: Aseo y cafetería | G3: Soporte IT BUN | H3: Canon arriendo oficina MED | I3: Plan exequial colaboradores | J3: Arriendo bodega | K3: Administración oficina CTG | L3: Administración oficina BRQ | M3: Plan preferencial | N3: Servicios públicos CALI | O3: Servicios públicos MED | P3: Teléfono fijo BOG | Q3: Cuota FITAC BOG | R3: Donación fundación techo | S3: Soporte IT CTG | T3: SD WAN | U3: Recolección basura AERPTO | V3: Servicios públicos BUN | W3: Arriendo bodega BUN | X3: Parqueadero BOG | Y3: Sistema nómina y SS | Z3: Arriendo bodega externa | AA3: Aseo oficina BUN | AB3: Canon arriendo oficina BRQ | AC3: Medicina prepagada | AD3: Datos celulares BOG | AE3: Arriendo fotocopiadora BUN | AF3: Gastos reembolsables aeropuerto | AG3: Canon arriendo oficina | AH3: Canon arriendo aeropuerto | AI3: Canon arriendo oficina CTG | AJ3: Aseo oficina MED | AK3: Canon arriendo oficina CALI | AL3: Soporte VeamBackup | AM3: Arriendo bodega CTG | AN3: Mensajería nacional | AO3: Acueducto BRQ | AP3: Internet MED | AQ3: SERV1
A4: ASTURIAS SOLUCIONES DE INGENIERIA BUCEO COMERCIAL Y DRAGADO SAS | C4: Administración oficina BUN | D4: Aseo oficina CALI | E4: SIM tablet CTG | F4: Papelería | J4: Administración oficina | K4: Servicios públicos CTG | M4: Áreas protegidas | Q4: Cuota FITAC CTG | T4: Internet todas las sucursales | AD4: Datos celulares CTG | AH4: Servicios públicos aeropuerto | AP4: Teléfono fijo MED | AQ4: SERV2
A5: CASALIMPIA SA | E5: Datos móviles BOG | J5: Servicios públicos | K5: Parqueadero CTG | Q5: Cuota FITAC BUN | AD5: Datos celulares BUN | AP5: Número único MED
A6: CLARO S.A. | E6: Internet oficinas CTG y BUN
A7: COMPAÑIA PAPELERA NACIONAL S.A.S | E7: Internet oficinas BRQ
A8: COMPUASOCIADOS | E8: Internet y telefonía CALI
A9: CONTRATOS Y FIANZAS DE ARRENDAMIENTO S.A.S. | E9: Telefonía fija BUN y CTG
A10: COORSERPARK | E10: Celulares colaboradores
A11: EDIFICIO CAPITAL TOWERS PROPIEDAD HORIZONTAL
A12: EDIFICIO PORTUS MANGA CARTAGENA
A13: EDIFICIO TORRES DEL ATLANTICO
A14: EMERMEDICA S.A.
A15: EMPRESAS MUNICIPALES DE CALI
A16: EMPRESAS PÚBLICAS DE MEDELLÍN E.S.P
A17: ETB S.A. E.S.P
A18: FEDERACION COLOMBIANA AGENTES LOGISTICOS
A19: FUNDACION UN TECHO PARA MI PAIS COLOMBIA
A20: HARDSOFT SOLUTIONS INTEGRAL SAS
A21: IFX NETWORKS COLOMBIA S.A.S.
A22: INTERASEO AEROPUERTO
... A44: PRUEBA

Sheet REGISTRO
A1: REGISTRO DE FACTURAS — CRAFT | Paso 1: elige PROVEEDOR → Paso 2: elige SERVICIO → completa los campos amarillos
A2: 🟨 Campos amarillos = ingreso manual | 🟩 Campos verdes = automáticos (no editar) | El SERVICIO depende del PROVEEDOR elegido
A3: N° | B3: PROVEEDOR | C3: SERVICIO | D3: ÁREA | E3: P&L | F3: CUENTA CONTABLE | G3: GLOSA | H3: TIPO | I3: DETALLE DEL GASTO | J3: SUCURSAL | K3: N° FACTURA | L3: FECHA INGRESO | M3: FECHA REALIZACIÓN | N3: FECHA VENCIMIENTO | O3: MONTO FACTURA | P3: IVA | Q3: RETENCIÓN | R3: GASTO NETO | S3: MES EJECUCIÓN | T3: CDC | U3: FECHA PROCESADO FINANCIERO | V3: FECHA DE PAGO | W3: SOLICITANTE | X3: OBSERVACIONES | Y3: APROBACIÓN GERENCIA ADMINISTRATIVA | Z3: FECHA DE APROBACIÓN
A4: 1 | B4: JOSE JOAQIN ALARCON | I4: LAVAR CORINAS OF 802 CRAFT BOGOTA | K4: 23 | L4: 45672 | M4: 45672 | N4: 45674 | O4: 950000 | P4: 0 | Q4: 0 | R4: 950000 | S4: enero 2025 | T4: 3127 | X4: aprobado por correo | Y4: Aprobado
A5: 2 | B5: COMPAÑIA PAPELERA NACIONAL S.A.S | I5: PEDIDO ASEO CAFETERIA Y PAPELERIA SUC CRAFT MEDELLIN | K5: CPFP159410 | L5: 45672 | M5: 45672 | N5: 45702 | O5: 460019 | P5: 0 | Q5: 0 | R5: 460019 | S5: enero 2025 | T5: 41 | Y5: Aprobado
A6: 3 | B6: CASALIMPIA SA | D6: ADM | F6: Otros Gastos CASA LIMPIA PLANILLA AC OTROS | I6: SERVICIO DE ASEO GENERAL OFICINA CRAFT CARTAGENA | J6: Cartagena | K6: 1715986 | L6: 45672 | M6: 45672 | N6: 45702 | O6: 1695582 | P6: 0 | Q6: 0 | R6: 1695582 | S6: enero 2025 | T6: 15 | Y6: Aprobado
A7: 4 | B7: JAVIER ANTONIO SANCHEZ | I7: ARRIENDO CUARTO DE BODEGA CRAFT BUENAVENTURA | K7: 2025-01 | L7: 45672 | M7: 45672 | N7: 45681 | O7: 250000 | P7: 0 | Q7: 0 | R7: 250000 | S7: enero 2025 | T7: 13 | X7: aprobado por correo | Y7: Aprobado
A8: 5 | B8: MOVISTAR | I8: SERVICIO LINEAS CELULARES CRAFT BOGOTA | K8: BEC428170024 | L8: 45672 | M8: 45674 | N8: 45678 | O8: 1654002 | P8: 0 | Q8: 0 | R8: 1654002 | S8: enero 2025 | T8: 3587 | Y8: Aprobado
A9: 6 | B9: Controles Empresariales SAS | I9: RENOVACION DE SOPORTE DEL SERVIDOR | K9: FEI0000083306 | L9: 45674 | M9: 45674 | N9: 45674 | O9: 17314732 | P9: 0 | Q9: 0 | R9: 17314732 | S9: enero 2025 | T9: 4062 | Y9: Aprobado
A10: 7 | B10: COMPAÑIA PAPELERA NACIONAL S.A.S | I10: PEDIDO PAPELERIA CRAFT BOGOTA | K10: CPFP159834 | L10: 45674 | M10: 45674 | N10: 45704 | O10: 131711 | P10: 0 | Q10: 0 | R10: 131711 | S10: enero 2025 | T10: 3724 | Y10: Aprobado
A11: 8 | B11: FUNDACION UN TECHO PARA MI PAIS COLOMBIA | I11: DONACION CON TRABAJOS ASOCIADOS CON LA RAZON SOCIAL | K11: FS74 | L11: 45674 | M11: 45674 | N11: 45674 | O11: 100000 | P11: 0 | Q11: 0 | R11: 100000 | S11: enero 2025 | T11: 3728 | Y11: Aprobado
A12: 9 | B12: PC QUICK SAS | I12: 3 PORTATIL PARA GRACE FONSECA, PAULA RODRIGUEZ, NICOLAS SALDAÑA | K12: PFE8206 | L12: 45673 | M12: 45674 | N12: 45703 | O12: 7321320 | P12: 0 | Q12: 0 | R12: 7321320 | S12: enero 2025 | T12: 3740 | Y12: Aprobado
A13: 10 | B13: CHATOBRAND SAS | I13: SELLO FECHADOR PARA CRAFT BUN // IMPRESION VINILOS ADHESIVOS | K13: FEV207 | L13: 45672 | M13: 45674 | N13: 45681 | O13: 232050 | P13: 0 | Q13: 0 | R13: 232050 | S13: enero 2025 | T13: 3773 | Y13: Aprobado
A14: 11 | B14: OPAIN SA AEROPUERTO EL DORADO | I14: GASTOS REEMBOLSABLES CRAFT AEROPUERTO | K14: CCG-18598 | L14: 45672 | M14: 45674 | N14: 45681 | O14: 568140 | P14: 0 | Q14: 0 | R14: 568140 | S14: enero 2025 | T14: 4 | X14: aprobado por correo | Y14: Aprobado
A15: 12 | B15: CLARO S.A. | I15: SIM TABLET BUN Y AEROPUERTO | K15: E5895019052 | L15: 45676 | M15: 45677 | O15: 295057 | P15: 0 | Q15: 0 | R15: 295057 | S15: enero 2025 | T15: 18 | Y15: Aprobado
A16: 13 | B16: CLARO S.A. | I16: SIM TABLET CTG | K16: E5894996021 | L16: 45676 | M16: 45677 | O16: 174625 | P16: 0 | Q16: 0 | R16: 174625 | S16: enero 2025 | T16: 17 | Y16: Aprobado
A17: 14 | B17: COMPAÑIA ANDINA DE SEGURIDAD PRIVADA BIC LTDA. - ANDISEG BIC LTDA | I17: VISITAS DE SEGURIDAD ASOCIADOS DE NEGOCIO | K17: ANDI20822. | L17: 45677 | M17: 45678 | N17: 45707 | O17: 618800 | P17: 0 | Q17: 0 | R17: 618800 | S17: enero 2025 | T17: 4342 | Y17: Aprobado
A18: 15 | B18: PC QUICK SAS | I18: PANTALLA LED PARA PC DE CAROLINA AMAYA | K18: PFE8209 | L18: 45677 | M18: 45678 | N18: 45707 | O18: 267750 | P18: 0 | Q18: 0 | R18: 267750 | S18: enero 2025 | T18: 4441 | Y18: Aprobado
A19: 16 | B19: AIR-E | I19: SERVICIO ENERGIA CRAFT BARRANQUILLA | K19: 91888743 | L19: 45678 | M19: 45678 | N19: 45678 | O19: 144670 | P19: 0 | Q19: 0 | R19: 144670 | S19: enero 2025 | T19: 4 | X19: aprobado por correo | Y19: Aprobado
A20: 17 | B20: ETIQUETAS COMERCIALES SAS | I20: ETIQUETEADORA PARA MARCAR ACTIVOS DE CRAFT | K20: FE3515 | L20: 45678 | M20: 45684 | N20: 45708 | O20: 232050 | P20: 0 | Q20: 0 | R20: 232050 | S20: enero 2025 | T20: 6325 | Y20: Aprobado
A21: 18 | B21: MULTICOPY JV ZOMAC SAS | I21: ALQUILER IMPRESORA CRAFT BUENAVENTURA | K21: FEPP6183 | L21: 45679 | M21: 45684 | N21: 45688 | O21: 196000 | P21: 0 | Q21: 0 | R21: 196000 | S21: enero 2025 | T21: 27 | Y21: Aprobado
A22: 19 | B22: MOVISTAR | I22: SERVICIO CELULARES CRAFT CARTAGENA | K22: BEC429616443 | L22: 45680 | M22: 45684 | N22: 45686 | O22: 804450 | P22: 0 | Q22: 0 | R22: 804450 | S22: enero 2025 | T22: 23 | Y22: Aprobado
A23: 20 | B23: HARDSOFT SOLUTIONS INTEGRAL SAS | I23: MANTENIMIENTO IT EN CTG | K23: HS152 | L23: 45681 | M23: 45684 | N23: 45688 | O23: 525980 | P23: 0 | Q23: 0 | R23: 525980 | S23: enero 2025 | T23: 24 | Y23: Aprobado
A24: 21 | B24: OPEN GROUP SAS | I24: camila.bravo, edwin ramirez, cambio de teclado de paola pulecio, uno que va hacer para carolina lopez y uno en stock para la persona de barranquilla | K24: FE5664 | L24: 45679 | M24: 45684 | N24: 45710 | O24: 574046 | P24: 0 | Q24: 0 | R24: 574046 | S24: enero 2025 | T24: 6325 | Y24: Aprobado
A25: 22 | B25: CASALIMPIA SA | D25: ADM | F25: Otros Gastos CASA LIMPIA PLANILLA AC OTROS | I25: SERVICIO DE ASEO GENERAL OFICINA CRAFT CARTAGENA | J25: Cartagena | K25: 1717328 | O25: 1358298 | P25: 0 | Q25: 0 | R25: 1358298 | S25: enero 2025 | T25: 25 | Y25: Aprobado
A26: 23 | B26: AAA ACUEDUCTO BARRANQUILLA | I26: SERVICIO ACUEDUCTO BARRANQUILLA | K26: 59843005 | O26: 226591 | P26: 0 | Q26: 0 | R26: 226591 | S26: enero 2025 | T26: 5 | Y26: Aprobado
A27: 24 | B27: Controles Empresariales SAS | I27: DIADEMAS 1 CAMILA BRAVO 4 EN STOCK | K27: FEI0000083772 | O27: 626350 | P27: 0 | Q27: 0 | R27: 626350 | S27: enero 2025 | T27: 6387 | Y27: Aprobado
A28: 25 | B28: JOAQUIN ALARCON | I28: ARREGLOS LOCATIVOS AEROPUERTO | K28: 24 | L28: 45686 | M28: 45686 | N28: 45688 | O28: 800000 | P28: 0 | Q28: 0 | R28: 800000 | S28: enero 2025 | T28: 6 | Y28: Aprobado
A29: 26 | B29: TIGO | I29: SERVICIO TELEFONIA FIJA SUC CRAFT MEDELLIN | K29: BOPU115668512 | L29: 45687 | M29: 45687 | N29: 45703 | O29: 109457 | P29: 0 | Q29: 0 | R29: 109457 | S29: enero 2025 | T29: 74 | Y29: Aprobado
A30: 27 | B30: TIGO | I30: SERVICIO DE NUMERO UNICO SUC CRAFT MEDELLIN | K30: BOPU115605001 | L30: 45687 | M30: 45687 | N30: 45703 | O30: 27351 | P30: 0 | Q30: 0 | R30: 27351 | S30: enero 2025 | T30: 73 | Y30: Aprobado
A31: 28 | B31: TIGO | I31: SERVICIO INTERNET SUC CRAFT MEDELLIN | K31: BOPU115616671 | L31: 45687 | M31: 45687 | N31: 45703 | O31: 131449 | P31: 0 | Q31: 0 | R31: 131449 | S31: enero 2025 | T31: 72 | Y31: Aprobado
A32: 29 | B32: MOVISTAR | I32: REPOSICION SIMCARD 3160231961 EN STOCK | K32: BEV21329050 | L32: 45687 | N32: 45702 | O32: 8000 | P32: 0 | Q32: 0 | R32: 8000 | S32: enero 2025 | T32: 7368 | Y32: Aprobado
A33: 30 | B33: OPERADORA HOTELERA PORTUS SAS | I33: ALOJAMIENTO EN CARTAGENA OLGA MONTOYA | K33: FEHM43364 | L33: 45702 | M33: 45705 | N33: 45732 | O33: 1356600 | P33: 0 | Q33: 0 | R33: 1356600 | S33: febrero 2025 | T33: 32 | Y33: Aprobado
A34: 31 | B34: PC QUICK SAS | I34: 2 PC / MEMORIAS GINNA CASTRO Y SEBASTIAN PEREZ | K34: PFE8349 | L34: 45702 | M34: 45705 | N34: 45732 | O34: 4680880 | P34: 0 | Q34: 0 | R34: 4680880 | S34: febrero 2025 | T34: 5530 | Y34: Aprobado
A35: 32 | B35: CONTRATOS Y FIANZAS DE ARRENDAMIENTO S.A.S. | D35: ADM | F35: Arriendos | I35: SERVICIO ZONA VIRTUAL CRAFT MEDELLIN | J35: Medellín | K35: FE566213 | L35: 45702 | M35: 45705 | N35: 45709 | O35: 5200 | P35: 0 | Q35: 0 | R35: 5200 | S35: febrero 2025 | T35: 97 | Y35: Aprobado
A36: 33 | B36: AIR-E | I36: SERVICIO ENERGIA CRAFT BARRANQUILLA | K36: 93439397 | L36: 45705 | M36: 45705 | N36: 45706 | O36: 547310 | P36: 0 | Q36: 0 | R36: 547310 | S36: febrero 2025 | T36: 3 | Y36: Aprobado
A37: 34 | B37: EPM MEDELLIN | I37: SERVICIOS PUBLICOS CRAFT MEDELLIN | K37: DEE9073074 | L37: 45705 | M37: 45705 | N37: 45715 | O37: 388061 | P37: 0 | Q37: 0 | R37: 388061 | S37: febrero 2025 | T37: 100 | Y37: Aprobado
A38: 35 | B38: MOVISTAR | I38: SERVICIOS CELULARES CRAFT BOGOTA | K38: BEC434656594 | L38: 45703 | M38: 45705 | N38: 45709 | O38: 1608263 | P38: 0 | Q38: 0 | R38: 1608263 | S38: febrero 2025 | T38: 5533 | Y38: Aprobado
A39: 36 | B39: JAVIER ANTONIO SANCHEZ | I39: ARRIENDO CUARTO DE BODEGA CRAFT BUENAVENTURA | K39: 202502 | L39: 45706 | M39: 45706 | N39: 45709 | O39: 250000 | P39: 0 | Q39: 0 | R39: 250000 | S39: febrero 2025 | T39: 11 | Y39: Aprobado
A40: 37 | B40: EDIFICIO PORTUS MANGA CARTAGENA | I40: PARQUEADERO EN CRAFT CARTAGENA | K40: 222 | L40: 45706 | M40: 45706 | N40: 45709 | O40: 94225 | P40: 0 | Q40: 0 | R40: 94225 | S40: febrero 2025 | T40: 20
A41: 38 | B41: JOAQUIN ALARCON | I41: ARREGLOS LOCATIVOS, SILLAS, DESTRUCICION ARVHIVO MUERTO CARPETAS | K41: 26 | L41: 45707 | M41: 45707 | N41: 45709 | O41: 700000 | P41: 0 | Q41: 0 | R41: 700000 | S41: febrero 2025 | T41: 4672 | Y41: Aprobado
A42: 39 | B42: AAA ACUEDUCTO BARRANQUILLA | I42: SERVICIO ACUEDUCTO CRAFT BARRANQUILLA | K42: 60555943 | L42: 45707 | M42: 45707 | N42: 45707 | O42: 221075 | P42: 0 | Q42: 0 | R42: 221075 | S42: febrero 2025 | T42: 4 | Y42: Aprobado
A43: 40 | B43: CLARO S.A. | I43: INTERNTE APTO CAROLINA TORRES EN PROCESO DE DESCONEXION | K43: R 1092424009 | L43: 45707 | M43: 45707 | N43: 45707 | O43: 155875 | P43: 0 | Q43: 0 | R43: 155875 | S43: febrero 2025 | T43: 6771 | X43: Aprobada por correo
A44: 41 | B44: TECNOLOGIA INFORMATICA TECINF SAS | I44: 5 COMBOS MOUSE NATALIA MAHECHA; GINNA CASTRO;SEBASTIAN;ISABELLAY VALENTINA | K44: FEB19459 | L44: 45705 | M44: 45707 | N44: 45735 | O44: 528734 | P44: 0 | Q44: 0 | R44: 528734 | S44: febrero 2025 | T44: 5573 | Y44: Aprobado
A45: 42 | B45: OPAIN SA AEROPUERTO EL DORADO | I45: AJUSTE GASTOS REEMBOLSABLES ENERO A MAR 2025 CRAFT AEROPUERTO | K45: CCG-19440 | O45: 204446 | P45: 0 | Q45: 0 | R45: 204446 | S45: enero 2025 | T45: 5
A46: 43 | B46: EPM MEDELLIN | I46: SERVICIOS PUBLICOS CRAFT MEDELLIN | K46: DEE14494551 | O46: 387631.52 | P46: 0 | Q46: 0 | R46: 387631.52 | S46: enero 2025 | T46: 57
A47: 44 | B47: Henry de jesus Sarmiento Rodriguez | I47: TRANSPORTE COLABORADORES CRAFT BOGOTA | K47: FE24 | O47: 3468500 | P47: 0 | Q47: 0 | R47: 3468500 | S47: =IF(M47="","",TEXT(M47,"mmmm yyyy")) | T47: 5575
A48: 45 | B48: CLARO S.A. | D48: IT | F48: Internet oficinas | H48: Fijo | I48: SERVICIO TV, INTERNET Y TELEFONIA CRAFT CALI | J48: Cali | K48: R1135520084 | O48: 170501 | P48: 0 | Q48: 0 | R48: 170501 | S48: enero 2025 | T48: 2
A49: 46 | B49: EDIFICIO CAPITAL TOWERS PROPIEDAD HORIZONTAL | D49: ADM | F49: Bodegas | H49: Fijo | I49: BODEGAS Y DEPOSITOS PISO 21 CRAFT BOGOTA | J49: Transversal | K49: FE9757 | O49: 1281274 | P49: 0 | Q49: 0 | R49: 1281274 | S49: enero 2025 | T49: 641
A50: 47 | B50: EDIFICIO CAPITAL TOWERS PROPIEDAD HORIZONTAL | D50: ADM | F50: Administración | H50: Fijo | I50: CUOTA DE ADMINISTRACION TORRE 1 CRAFT BOGOTA | J50: Calle 100 | K50: FE9730 | O50: 5000363 | P50: 0 | Q50: 0 | R50: 5000363 | S50: enero 2025 | T50: 642
A51: 48 | B51: JCO INVERSIONES S.A.S | D51: ADM | F51: Parqueaderos | H51: Fijo | I51: CANON ARRENDAMIENTO 2 ESPACIOS DE PARQUEADERO CRAFT BOGOTA | J51: Calle 100 | K51: 691512 | O51: 711870 | P51: 0 | Q51: 0 | R51: 711870 | S51: enero 2025 | T51: 644
A52: 49 | B52: IFX NETWORKS COLOMBIA S.A.S. | D52: IT | F52: Internet oficinas | H52: Fijo | I52: SERVICO DE INTERNET EN TODAS LAS SUCURSALES | J52: Transversal | K52: IFXC450271 | O52: 11576939 | P52: 0 | Q52: 0 | R52: 11576939 | S52: enero 2025 | T52: 916
A53: 50 | B53: IFX NETWORKS COLOMBIA S.A.S. | D53: IT | F53: Internet oficinas | H53: Fijo | I53: SERVICIO SD WAN | J53: Transversal | K53: IFXC450269 | O53: 3488538 | P53: 0 | Q53: 0 | R53: 3488538 | S53: enero 2025 | T53: 919
A54: 51 | B54: LI STORAGE SAS | D54: ADM | F54: Bodegas | H54: Fijo | I54: ALMACENAMIENTO EN BODEGA CRAFT BOGOTA | J54: Transversal | K54: FE5183 | O54: 654500 | P54: 0 | Q54: 0 | R54: 654500 | S54: enero 2025 | T54: 645
A55: 52 | B55: ASTURIAS SOLUCIONES DE INGENIERIA BUCEO COMERCIAL Y DRAGADO SAS | D55: ADM | F55: Administración | H55: Fijo | I55: CUOTA ADMINISTRCION OF 501 CRAFT BUENAVENTURA | J55: Buenaventura | K55: FVEL2687 | O55: 617412 | P55: 0 | Q55: 0 | R55: 617412 | S55: enero 2025 | T55: 3
A56: 53 | B56: ASTURIAS SOLUCIONES DE INGENIERIA BUCEO COMERCIAL Y DRAGADO SAS | D56: ADM | F56: Arriendos | H56: Fijo | I56: ALQUILER OFICINA 501 SUC CRAFT BUENAVENTURA | J56: Buenaventura | K56: FVEL2686 | O56: 6390966 | P56: 0 | Q56: 0 | R56: 6390966 | S56: enero 2025 | T56: 4
A57: 54 | B57: PALAN SOCIEDAD POR ACCIONES SIMPLIFICADA | D57: ADM | F57: Arriendos | H57: Fijo | I57: CANON ARRENDAMIENTO OF 802 SUC CRAFT BOGOTA | J57: Calle 100 | K57: FE272 | O57: 28741955 | P57: 0 | Q57: 0 | R57: 28741955 | S57: enero 2025 | T57: 651
A58: 55 | B58: CONTRATOS Y FIANZAS DE ARRENDAMIENTO S.A.S. | D58: ADM | F58: Arriendos | H58: Fijo | I58: CANON DE ARRENDAMIENTO CRAFT MEDELLIN | J58: Medellín | K58: FE578658 | O58: 6682717 | P58: 0 | Q58: 0 | R58: 6682717 | S58: enero 2025 | T58: 14
A59: 56 | B59: SUMAR INVERSIONES Y PROYECTOS S.A.S. | D59: ADM | F59: Arriendos | H59: Fijo | I59: CANON DE ARRENDAMIENTO Y ADMON CRAFT CALI | J59: Cali | K59: FESU252 | O59: 5310474 | P59: 0 | Q59: 0 | R59: 5310474 | S59: enero 2025 | T59: 1
... A77: 74 | B77: INTERASEO AEROPUERTO | D77: ADM | F77: Agua | H77: Fijo | I77: RECOLECCION BASURA CRAFT AEROPUERTO | J77: Aeropuerto | K77: INAE041388 | O77: 35808 | P77: 0 | Q77: 0 | R77: 35808 | S77: enero 2025 | T77: 3
A78: 75 | B78: JAVIER ANTONIO SANCHEZ | D78: ADM | F78: Bodegas | I78: ARRIENDO CUARTO DE BODEGA CRAFT BUENAVENTURA | J78: Buenaventura | K78: 202601 | O78: 250000 | P78: 0 | Q78: 0 | R78: 250000 | S78: enero 2025 | T78: 6
A79: 76 | B79: TRIPLE AAA | D79: ADM | F79: Agua | H79: Fijo | I79: SERVICIO ACUEDUCTO CRAFT BARRANQUILLA | J79: Barranquilla | K79: 68930122 | O79: 258014 | P79: 0 | Q79: 0 | R79: 258014 | S79: enero 2025 | T79: 3
A80: 77 | B80: CLARO S.A. | D80: ADM | F80: Telefono fijo | H80: Fijo | I80: SERVICIO DE TELEFONIA FIJA BUN Y CTG | J80: Puertos | K80: 3292477322 | O80: 168540 | P80: 0 | Q80: 0 | R80: 168540 | S80: enero 2025 | T80: 18
A81: 78 | B81: EDIFICIO PORTUS MANGA CARTAGENA | D81: ADM | F81: Administración | H81: Fijo | I81: EXPENSAS DE ADMINISTRACION CRAFT CARTAGENA | J81: Cartagena | K81: 967 | O81: 576439 | P81: 0 | Q81: 0 | R81: 576439 | S81: enero 2025 | T81: 20
A82: 79 | B82: TRAIKER GROUP COLOMBIA S.A.S. | D82: ADM | F82: Bodegas | I82: ALMACENAMIENTO DE CAJAS EN CRAFT CARTAGENA | J82: Cartagena | K82: FEA566 | O82: 434826 | P82: 0 | Q82: 0 | R82: 434826 | S82: enero 2025 | T82: 19
A83: 80 | B83: COMPAÑIA PAPELERA NACIONAL S.A.S | D83: ADM | F83: Material Copa/Cozinha | H83: Variable | I83: PEDIDO ASEO Y CAFETERIA CRAFT MEDELLIN | J83: Medellín | K83: CPFP196271 | O83: 153492 | P83: 0 | Q83: 0 | R83: 153492 | S83: enero 2025 | T83: 28
A84: 81 | B84: COMPAÑIA PAPELERA NACIONAL S.A.S | D84: ADM | F84: Material Copa/Cozinha | H84: Variable | I84: PEDIDO ASEO Y CAFETERIA CRAFT BUENAVENTURA | J84: Buenaventura | K84: CPFP196272 | O84: 1146245 | P84: 0 | Q84: 0 | R84: 1146245 | S84: enero 2025 | T84: 7
A85: 82 | B85: PATRIMONIOS AUTONOMOS FIDUCIARIA BANCOLOMBIA S A SOCIEDAD FIDUCIARIA | D85: ADM | F85: Arriendos | H85: Fijo | I85: CANON ARRENDAMIENTO SUCURSAL CRAFT AEROPUERTO | J85: Aeropuerto | K85: AR3170188 | O85: 7341058 | P85: 0 | Q85: 0 | R85: 7341058 | S85: enero 2025 | T85: 5
A86: 83 | B86: CLARO S.A. | D86: IT | F86: Internet oficinas | H86: Fijo | I86: SERVICIO INTERNET Y TELEFONIA CRAFT BARRANQUILLA | J86: Barranquilla | K86: R1135024782 | O86: 131985 | P86: 0 | Q86: 0 | R86: 131985 | S86: enero 2025 | T86: 4
A87: 84 | B87: COMPAÑIA PAPELERA NACIONAL S.A.S | D87: ADM | F87: Material Copa/Cozinha | H87: Variable | I87: PEDIDO ASEO Y CAFETERIA CRAFT CARTAGENA | J87: Cartagena | K87: CPFP196537 | O87: 877893 | P87: 0 | Q87: 0 | R87: 877893 | S87: enero 2025 | T87: 21
A88: 85 | B88: AIR-E | D88: ADM | F88: Luz | H88: Fijo | I88: SERVICIO ENERGIA CRAFT BARRANQUILLA | J88: Barranquilla | K88: 58914617 | O88: 316440 | P88: 0 | Q88: 0 | R88: 316440 | S88: enero 2025 | T88: 6
A89: 86 | B89: LUZ DARY MINA GARCES | D89: ADM | F89: Otros Gastos CASA LIMPIA PLANILLA AC OTROS | H89: Fijo | I89: SERVICIO ASEO GENERAL OFICINA CRAFT BUENAVENTURA | J89: Buenaventura | K89: 168 | O89: 1000000 | P89: 0 | Q89: 0 | R89: 1000000 | S89: enero 2025 | T89: 9
A90: 87 | B90: ETB | D90: ADM | F90: Telefono fijo | H90: Fijo | I90: SERVICIO DE TELEFONIA LOCAL PBX | J90: Calle 100 | K90: FC1000328577 | O90: 1013044 | P90: 0 | Q90: 0 | R90: 1013044 | S90: enero 2025 | T90: 3516
A91: 88 | B91: CASALIMPIA SA | D91: ADM | F91: Otros Gastos CASA LIMPIA PLANILLA AC OTROS | H91: Fijo | I91: SERVICIO DE ASEO GENERAL OFICINA CRAFT CARTAGENA | J91: Cartagena | K91: CL150207 | O91: 2088787 | P91: 0 | Q91: 0 | R91: 2088787 | S91: enero 2025 | T91: 24
A92: 89 | B92: COMPAÑIA PAPELERA NACIONAL S.A.S | D92: ADM | F92: Material Copa/Cozinha | H92: Variable | I92: PEDIDO ASEO Y CAFETERIA CRAFT CALLE 100 | J92: Calle 100 | K92: CPFP196835 | O92: 376613 | P92: 0 | Q92: 0 | R92: 376613 | S92: enero 2025 | T92: 3517
A93: 90 | B93: COMPAÑIA PAPELERA NACIONAL S.A.S | D93: ADM | F93: Material Copa/Cozinha | H93: Variable | I93: PEDIDO ASEO Y CAFETERIA CRAFT CALLE 100 | J93: Calle 100 | K93: CPFP196836 | O93: 173535 | P93: 0 | Q93: 0 | R93: 173535 | S93: enero 2025 | T93: 3519
A94: 91 | B94: CONTRATOS Y FIANZAS DE ARRENDAMIENTO S.A.S. | D94: ADM | F94: Arriendos | H94: Fijo | I94: SERVICIO ZONA VIRTUAL CRAFT MEDELLIN | J94: Medellín | K94: FE579607 | O94: 5200 | P94: 0 | Q94: 0 | R94: 5200 | S94: enero 2025 | T94: 36
... A100: 97 | B100: LUZ DARY MINA GARCES | D100: ADM | F100: Otros Gastos CASA LIMPIA PLANILLA AC OTROS | H100: Fijo | I100: SERVICIO ASEO GENERAL OFICINA CRAFT BUENAVENTURA | J100: Buenaventura | K100: 169 | O100: 1000000 | P100: 0 | Q100: 0 | R100: 1000000 | S100: enero 2025 | T100: 20
A101: 98 | B101: HARDSOFT SOLUTIONS INTEGRAL SAS | D101: IT | F101: Conservacion Y Manutenimiento De Oficina | I101: MANTENIMIENTO IT EN CTG | J101: Cartagena | K101: HS558 | O101: 581938 | P101: 0 | Q101: 0 | R101: 581938 | S101: enero 2025 | T101: 35
A102: 99 | B102: INVERSIONES HOTELERAS BUENAVENTURA S.A.S. | D102: ADM | F102: Agua | H102: Fijo | I102: RECOBRO SERVICIOS PUBLICOS DE CRAFT BUENAVENTURA | J102: Buenaventura | K102: RCE4077 | O102: 377160 | P102: 0 | Q102: 0 | R102: 377160 | S102: enero 2025 | T102: 24
A103: 100 | B103: TECNOLOGIA INFORMATICA TECINF SAS | D103: IT | F103: Repositorio Veembackup | H103: Fijo | I103: SERVICIOS VEAM BACKUP | J103: Transversal | K103: FEB25215 | O103: 2666664 | P103: 0 | Q103: 0 | R103: 2666664 | S103: enero 2025 | T103: 7119
A104: 101 | B104: PC QUICK SAS | D104: IT | F104: Insumos y perifericos | H104: Variable | I104: TECLADO PC LORENA AMAYA % EQUIPO DE BACKUP | J104: Transversal | K104: PFE9745 | O104: 1166200 | P104: 0 | Q104: 0 | R104: 1166200 | S104: enero 2025 | T104: 7123
A105: 102 | B105: EDIFICIO CAPITAL TOWERS PROPIEDAD HORIZONTAL | D105: ADM | F105: Agua | H105: Fijo | I105: RECOBRO SERVICIOS PUBLICOS CRAFT BOGOTA | J105: Calle 100 | K105: FE9796 | O105: 906599 | P105: 0 | Q105: 0 | R105: 906599 | S105: enero 2025 | T105: 7111
A106: 103 | B106: MULTICOPY JV ZOMAC SAS | D106: IT | F106: Conservacion Y Manutenimiento De Oficina | I106: ALQUILER IMPRESORA CRAFT BUENAVENTURA | J106: Buenaventura | K106: FEMC9363 | O106: 254548 | P106: 0 | Q106: 0 | R106: 254548 | S106: enero 2025 | T106: 22
A107: 104 | B107: IFX NETWORKS COLOMBIA S.A.S. | D107: IT | F107: Internet oficinas | H107: Fijo | I107: SERVICO DE INTERNET EN TODAS LAS SUCURSALES | J107: Transversal | K107: IFXC452773 | O107: 11618595 | P107: 0 | Q107: 0 | R107: 11618595 | S107: febrero 2025 | T107: 1685
A108: 105 | B108: IFX NETWORKS COLOMBIA S.A.S. | D108: IT | F108: Internet oficinas | H108: Fijo | I108: SERVICIO SD WAN | J108: Transversal | K108: IFXC452769 | O108: 3488538 | P108: 0 | Q108: 0 | R108: 3488538 | S108: febrero 2025 | T108: 1693
A109: 106 | B109: EPM MEDELLIN | D109: ADM | F109: Agua | H109: Fijo | I109: SERVICOS PUBLICOS CRAFT MEDELLIN | J109: Medellín | K109: DEE39136990 | O109: 348371 | P109: 0 | Q109: 0 | R109: 348371 | S109: febrero 2025 | T109: 37
A110: 107 | B110: TIGO | D110: IT | F110: Internet oficinas | H110: Fijo | I110: SERVICIO INTERNET CRAFT MEDELLIN | J110: Medellín | K110: BOPU130102182 | O110: 143404 | P110: 0 | Q110: 0 | R110: 143404 | S110: enero 2025 | T110: 58
A111: 108 | B111: TIGO | D111: ADM | F111: Telefono fijo | H111: Fijo | I111: SERVICIO NUMERO UNICO CRAFT MEDELLIN | J111: Medellín | K111: BOPU130091325 | O111: 27351 | P111: 0 | Q111: 0 | R111: 27351 | S111: enero 2025 | T111: 59
A112: 109 | B112: SERVICIO TELEFONIA FIJA CRAFT MEDELLIN | D112: ADM | F112: Telefono fijo | I112: SERVICIO TELEFONO FIJO CRAFT MEDELLIN | J112: Medellín | K112: BOPU130146802 | O112: 115030 | P112: 0 | Q112: 0 | R112: 115030 | S112: enero 2025 | T112: 60
A113: 110 | B113: ASTURIAS SOLUCIONES DE INGENIERIA BUCEO COMERCIAL Y DRAGADO SAS | D113: ADM | F113: Administración | H113: Fijo | I113: CUOTA ADMINISTRCION OF 501 CRAFT BUENAVENTURA | J113: Buenaventura | K113: FVEL2732 | O113: 680090 | P113: 0 | Q113: 0 | R113: 680090 | S113: febrero 2025 | T113: 6
A114: 111 | B114: ASTURIAS SOLUCIONES DE INGENIERIA BUCEO COMERCIAL Y DRAGADO SAS | I114: ALQUILER OFICINA 501 SUC CRAFT BUENAVENTURA | K114: FVEL2728 | O114: 6716906 | P114: 0 | Q114: 0 | R114: 6716906 | S114: febrero 2025
A115: 112 | B115: JCO INVERSIONES S.A.S | D115: ADM | F115: Parqueaderos | H115: Fijo | I115: CANON ARRENDAMIENTO 2 ESPACIOS DE PARQUEADERO CRAFT BOGOTA | J115: Calle 100 | K115: 693740 | O115: 711870 | P115: 0 | Q115: 0 | R115: 711870 | S115: febrero 2025 | T115: 622
A116: 113 | B116: SUMAR INVERSIONES Y PROYECTOS S.A.S. | D116: ADM | F116: Arriendos | H116: Fijo | I116: CANON DE ARRENDAMIENTO Y ADMON CRAFT CALI | J116: Cali | K116: FESU255 | O116: 5310474 | P116: 0 | Q116: 0 | R116: 5310474 | S116: febrero 2025 | T116: 1
A117: 114 | B117: LI STORAGE SAS | D117: ADM | F117: Bodegas | H117: Fijo | I117: ALMACENAMIENTO EN BODEGA CRAFT BOGOTA | J117: Transversal | K117: FE5211 | O117: 654500 | P117: 0 | Q117: 0 | R117: 654500 | S117: febrero 2025 | T117: 627
A118: 115 | B118: CONTRATOS Y FIANZAS DE ARRENDAMIENTO S.A.S. | D118: ADM | F118: Arriendos | H118: Fijo | I118: CANON DE ARRENDAMIENTO CRAFT MEDELLIN | J118: Medellín | K118: FE579903 | O118: 6682717 | P118: 0 | Q118: 0 | R118: 6682717 | S118: febrero 2025 | T118: 10
A119: 116 | B119: PORTUS GLOBAL SAS | D119: ADM | F119: Arriendos | H119: Fijo | I119: CANON DE ARRENDAMIENTO OF 1502 SUC CRAFT CARTAGENA | J119: Cartagena | K119: 717 | O119: 8477869 | P119: 0 | Q119: 0 | R119: 8477869 | S119: febrero 2025 | T119: 4
A120: 117 | B120: ASTURIAS SOLUCIONES DE INGENIERIA BUCEO COMERCIAL Y DRAGADO SAS | I120: NC AFECTA FACTURA FVEL2728 | K120: NC1331 | O120: 6716906 | P120: 0 | Q120: 0 | R120: 6716906 | S120: febrero 2025
A121: 118 | B121: COMPUASOCIADOS | D121: IT | F121: Conservacion Y Manutenimiento De Oficina | H121: Fijo | I121: SOPORTE TECNICO IT EQUPOS CCTV E IMPRESORA EN CRAFT BUENAVENTURA | J121: Buenaventura | K121: 3797 | O121: 390000 | P121: 0 | Q121: 0 | R121: 390000 | S121: febrero 2025 | T121: 8
A122: 119 | B122: CLARO S.A. | D122: IT | F122: Internet oficinas | H122: Fijo | I122: SERVICIO TV, INTERNET Y TELEFONIA CRAFT CALI | J122: Cali | K122: R1139225061 | O122: 170501 | P122: 0 | Q122: 0 | R122: 170501 | S122: febrero 2025 | T122: 2
...

Sheet ARCHIVO PLANO
A1: ARCHIVO PLANO — PARA CONTABILIDAD | Generado automáticamente desde REGISTRO
A2: N° | B2: PROVEEDOR | C2: SERVICIO | D2: ÁREA | E2: P&L | F2: CUENTA CONTABLE | G2: GLOSA | H2: DETALLE | I2: SUCURSAL | J2: N° FACTURA | K2: FECHA VENCIMIENTO | L2: GASTO NETO | M2: MES EJECUCIÓN
A3: =IF(REGISTRO!B4="","",REGISTRO!A4) | B3: =IF(REGISTRO!B4="","",REGISTRO!B4) | C3: =IF(REGISTRO!B4="","",REGISTRO!C4) | D3: =IF(REGISTRO!B4="","",REGISTRO!D4) | E3: =IF(REGISTRO!B4="","",REGISTRO!E4) | F3: =IF(REGISTRO!B4="","",REGISTRO!F4) | G3: =IF(REGISTRO!B4="","",REGISTRO!G4) | H3: =IF(REGISTRO!B4="","",REGISTRO!I4) | I3: =IF(REGISTRO!B4="","",REGISTRO!J4) | J3: =IF(REGISTRO!B4="","",REGISTRO!K4) | K3: =IF(REGISTRO!B4="","",REGISTRO!N4) | L3: =IF(REGISTRO!B4="","",REGISTRO!R4) | M3: =IF(REGISTRO!B4="","",REGISTRO!S4)
A4: =IF(REGISTRO!B4="","",REGISTRO!A4) | B4: =IF(REGISTRO!B4="","",REGISTRO!B4) | C4: =IF(REGISTRO!B4="","",REGISTRO!C4) | D4: =IF(REGISTRO!B4="","",REGISTRO!D4) | E4: =IF(REGISTRO!B4="","",REGISTRO!E4) | F4: =IF(REGISTRO!B4="","",REGISTRO!F4) | G4: =IF(REGISTRO!B4="","",REGISTRO!G4) | H4: =IF(REGISTRO!B4="","",REGISTRO!I4) | I4: =IF(REGISTRO!B4="","",REGISTRO!J4) | J4: =IF(REGISTRO!B4="","",REGISTRO!K4) | K4: =IF(REGISTRO!B4="","",REGISTRO!N4) | L4: =IF(REGISTRO!B4="","",REGISTRO!R4) | M4: =IF(REGISTRO!B4="","",REGISTRO!S4)
A5: =IF(REGISTRO!B5="","",REGISTRO!A5) | B5: =IF(REGISTRO!B5="","",REGISTRO!B5) | C5: =IF(REGISTRO!B5="","",REGISTRO!C5) | D5: =IF(REGISTRO!B5="","",REGISTRO!D5) | E5: =IF(REGISTRO!B5="","",REGISTRO!E5) | F5: =IF(REGISTRO!B5="","",REGISTRO!F5) | G5: =IF(REGISTRO!B5="","",REGISTRO!G5) | H5: =IF(REGISTRO!B5="","",REGISTRO!I5) | I5: =IF(REGISTRO!B5="","",REGISTRO!J5) | J5: =IF(REGISTRO!B5="","",REGISTRO!K5) | K5: =IF(REGISTRO!B5="","",REGISTRO!N5) | L5: =IF(REGISTRO!B5="","",REGISTRO!R5) | M5: =IF(REGISTRO!B5="","",REGISTRO!S5)
A6: =IF(REGISTRO!B6="","",REGISTRO!A6) | B6: =IF(REGISTRO!B6="","",REGISTRO!B6) | C6: =IF(REGISTRO!B6="","",REGISTRO!C6) | D6: =IF(REGISTRO!B6="","",REGISTRO!D6) | E6: =IF(REGISTRO!B6="","",REGISTRO!E6) | F6: =IF(REGISTRO!B6="","",REGISTRO!F6) | G6: =IF(REGISTRO!B6="","",REGISTRO!G6) | H6: =IF(REGISTRO!B6="","",REGISTRO!I6) | I6: =IF(REGISTRO!B6="","",REGISTRO!J6) | J6: =IF(REGISTRO!B6="","",REGISTRO!K6) | K6: =IF(REGISTRO!B6="","",REGISTRO!N6) | L6: =IF(REGISTRO!B6="","",REGISTRO!R6) | M6: =IF(REGISTRO!B6="","",REGISTRO!S6)
A7: =IF(REGISTRO!B7="","",REGISTRO!A7) | B7: =IF(REGISTRO!B7="","",REGISTRO!B7) | C7: =IF(REGISTRO!B7="","",REGISTRO!C7) | D7: =IF(REGISTRO!B7="","",REGISTRO!D7) | E7: =IF(REGISTRO!B7="","",REGISTRO!E7) | F7: =IF(REGISTRO!B7="","",REGISTRO!F7) | G7: =IF(REGISTRO!B7="","",REGISTRO!G7) | H7: =IF(REGISTRO!B7="","",REGISTRO!I7) | I7: =IF(REGISTRO!B7="","",REGISTRO!J7) | J7: =IF(REGISTRO!B7="","",REGISTRO!K7) | K7: =IF(REGISTRO!B7="","",REGISTRO!N7) | L7: =IF(REGISTRO!B7="","",REGISTRO!R7) | M7: =IF(REGISTRO!B7="","",REGISTRO!S7)
A8: =IF(REGISTRO!B8="","",REGISTRO!A8) | B8: =IF(REGISTRO!B8="","",REGISTRO!B8) | C8: =IF(REGISTRO!B8="","",REGISTRO!C8) | D8: =IF(REGISTRO!B8="","",REGISTRO!D8) | E8: =IF(REGISTRO!B8="","",REGISTRO!E8) | F8: =IF(REGISTRO!B8="","",REGISTRO!F8) | G8: =IF(REGISTRO!B8="","",REGISTRO!G8) | H8: =IF(REGISTRO!B8="","",REGISTRO!I8) | I8: =IF(REGISTRO!B8="","",REGISTRO!J8) | J8: =IF(REGISTRO!B8="","",REGISTRO!K8) | K8: =IF(REGISTRO!B8="","",REGISTRO!N8) | L8: =IF(REGISTRO!B8="","",REGISTRO!R8) | M8: =IF(REGISTRO!B8="","",REGISTRO!S8)
A9: =IF(REGISTRO!B9="","",REGISTRO!A9) | B9: =IF(REGISTRO!B9="","",REGISTRO!B9) | C9: =IF(REGISTRO!B9="","",REGISTRO!C9) | D9: =IF(REGISTRO!B9="","",REGISTRO!D9) | E9: =IF(REGISTRO!B9="","",REGISTRO!E9) | F9: =IF(REGISTRO!B9="","",REGISTRO!F9) | G9: =IF(REGISTRO!B9="","",REGISTRO!G9) | H9: =IF(REGISTRO!B9="","",REGISTRO!I9) | I9: =IF(REGISTRO!B9="","",REGISTRO!J9) | J9: =IF(REGISTRO!B9="","",REGISTRO!K9) | K9: =IF(REGISTRO!B9="","",REGISTRO!N9) | L9: =IF(REGISTRO!B9="","",REGISTRO!R9) | M9: =IF(REGISTRO!B9="","",REGISTRO!S9)
A10: =IF(REGISTRO!B10="","",REGISTRO!A10) | B10: =IF(REGISTRO!B10="","",REGISTRO!B10) | C10: =IF(REGISTRO!B10="","",REGISTRO!C10) | D10: =IF(REGISTRO!B10="","",REGISTRO!D10) | E10: =IF(REGISTRO!B10="","",REGISTRO!E10) | F10: =IF(REGISTRO!B10="","",REGISTRO!F10) | G10: =IF(REGISTRO!B10="","",REGISTRO!G10) | H10: =IF(REGISTRO!B10="","",REGISTRO!I10) | I10: =IF(REGISTRO!B10="","",REGISTRO!J10) | J10: =IF(REGISTRO!B10="","",REGISTRO!K10) | K10: =IF(REGISTRO!B10="","",REGISTRO!N10) | L10: =IF(REGISTRO!B10="","",REGISTRO!R10) | M10: =IF(REGISTRO!B10="","",REGISTRO!S10)
A11: =IF(REGISTRO!B11="","",REGISTRO!A11) | B11: =IF(REGISTRO!B11="","",REGISTRO!B11) | C11: =IF(REGISTRO!B11="","",REGISTRO!C11) | D11: =IF(REGISTRO!B11="","",REGISTRO!D11) | E11: =IF(REGISTRO!B11="","",REGISTRO!E11) | F11: =IF(REGISTRO!B11="","",REGISTRO!F11) | G11: =IF(REGISTRO!B11="","",REGISTRO!G11) | H11: =IF(REGISTRO!B11="","",REGISTRO!I11) | I11: =IF(REGISTRO!B11="","",REGISTRO!J11) | J11: =IF(REGISTRO!B11="","",REGISTRO!K11) | K11: =IF(REGISTRO!B11="","",REGISTRO!N11) | L11: =IF(REGISTRO!B11="","",REGISTRO!R11) | M11: =IF(REGISTRO!B11="","",REGISTRO!S11)
A12: =IF(REGISTRO!B12="","",REGISTRO!A12) | B12: =IF(REGISTRO!B12="","",REGISTRO!B12) | C12: =IF(REGISTRO!B12="","",REGISTRO!C12) | D12: =IF(REGISTRO!B12="","",REGISTRO!D12) | E12: =IF(REGISTRO!B12="","",REGISTRO!E12) | F12: =IF(REGISTRO!B12="","",REGISTRO!F12) | G12: =IF(REGISTRO!B12="","",REGISTRO!G12) | H12: =IF(REGISTRO!B12="","",REGISTRO!I12) | I12: =IF(REGISTRO!B12="","",REGISTRO!J12) | J12: =IF(REGISTRO!B12="","",REGISTRO!K12) | K12: =IF(REGISTRO!B12="","",REGISTRO!N12) | L12: =IF(REGISTRO!B12="","",REGISTRO!R12) | M12: =IF(REGISTRO!B12="","",REGISTRO!S12)
A13: =IF(REGISTRO!B13="","",REGISTRO!A13) | B13: =IF(REGISTRO!B13="","",REGISTRO!B13) | C13: =IF(REGISTRO!B13="","",REGISTRO!C13) | D13: =IF(REGISTRO!B13="","",REGISTRO!D13) | E13: =IF(REGISTRO!B13="","",REGISTRO!E13) | F13: =IF(REGISTRO!B13="","",REGISTRO!F13) | G13: =IF(REGISTRO!B13="","",REGISTRO!G13) | H13: =IF(REGISTRO!B13="","",REGISTRO!I13) | I13: =IF(REGISTRO!B13="","",REGISTRO!J13) | J13: =IF(REGISTRO!B13="","",REGISTRO!K13) | K13: =IF(REGISTRO!B13="","",REGISTRO!N13) | L13: =IF(REGISTRO!B13="","",REGISTRO!R13) | M13: =IF(REGISTRO!B13="","",REGISTRO!S13)
A14: =IF(REGISTRO!B14="","",REGISTRO!A14) | B14: =IF(REGISTRO!B14="","",REGISTRO!B14) | C14: =IF(REGISTRO!B14="","",REGISTRO!C14) | D14: =IF(REGISTRO!B14="","",REGISTRO!D14) | E14: =IF(REGISTRO!B14="","",REGISTRO!E14) | F14: =IF(REGISTRO!B14="","",REGISTRO!F14) | G14: =IF(REGISTRO!B14="","",REGISTRO!G14) | H14: =IF(REGISTRO!B14="","",REGISTRO!I14) | I14: =IF(REGISTRO!B14="","",REGISTRO!J14) | J14: =IF(REGISTRO!B14="","",REGISTRO!K14) | K14: =IF(REGISTRO!B14="","",REGISTRO!N14) | L14: =IF(REGISTRO!B14="","",REGISTRO!R14) | M14: =IF(REGISTRO!B14="","",REGISTRO!S14)
A15: =IF(REGISTRO!B15="","",REGISTRO!A15) | B15: =IF(REGISTRO!B15="","",REGISTRO!B15) | C15: =IF(REGISTRO!B15="","",REGISTRO!C15) | D15: =IF(REGISTRO!B15="","",REGISTRO!D15) | E15: =IF(REGISTRO!B15="","",REGISTRO!E15) | F15: =IF(REGISTRO!B15="","",REGISTRO!F15) | G15: =IF(REGISTRO!B15="","",REGISTRO!G15) | H15: =IF(REGISTRO!B15="","",REGISTRO!I15) | I15: =IF(REGISTRO!B15="","",REGISTRO!J15) | J15: =IF(REGISTRO!B15="","",REGISTRO!K15) | K15: =IF(REGISTRO!B15="","",REGISTRO!N15) | L15: =IF(REGISTRO!B15="","",REGISTRO!R15) | M15: =IF(REGISTRO!B15="","",REGISTRO!S15)
... A451: =IF(REGISTRO!B451="","",REGISTRO!A451) | B451: =IF(REGISTRO!B451="","",REGISTRO!B451) | C451: =IF(REGISTRO!B451="","",REGISTRO!C451) | D451: =IF(REGISTRO!B451="","",REGISTRO!D451) | E451: =IF(REGISTRO!B451="","",REGISTRO!E451) | F451: =IF(REGISTRO!B451="","",REGISTRO!F451) | G451: =IF(REGISTRO!B451="","",REGISTRO!G451) | H451: =IF(REGISTRO!B451="","",REGISTRO!I451) | I451: =IF(REGISTRO!B451="","",REGISTRO!J451) | J451: =IF(REGISTRO!B451="","",REGISTRO!K451) | K451: =IF(REGISTRO!B451="","",REGISTRO!N451) | L451: =IF(REGISTRO!B451="","",REGISTRO!R451) | M451: =IF(REGISTRO!B451="","",REGISTRO!S451)

Sheet REGISTRO NO PAGAR
A1: REGISTRO DE FACTURAS NO PAGAR — CRAFT | Paso 1: elige PROVEEDOR → Paso 2: elige SERVICIO → completa los campos amarillos
A2: 🟨 Campos amarillos = ingreso manual | 🟩 Campos verdes = automáticos (no editar) | El SERVICIO depende del PROVEEDOR elegido | Facturas que NO se van a pagar (rechazadas / dadas de baja)
A3: N° | B3: PROVEEDOR | C3: SERVICIO | D3: ÁREA | E3: P&L | F3: CUENTA CONTABLE | G3: GLOSA | H3: TIPO | I3: DETALLE DEL GASTO | J3: SUCURSAL | K3: N° FACTURA | L3: FECHA FACTURA | M3: FECHA REALIZACIÓN EVENTOS | N3: MONTO | O3: CDC | P3: FECHA PROCESADO FINANCIERO | Q3: OBSERVACIONES | R3: APROBACIÓN GERENCIA ADMINISTRATIVA | S3: FECHA DE APROBACIÓN | T3: MES EJECUCIÓN
A4: 1 | B4: CASALIMPIA SA | D4: ADM | E4: =IF(OR(B4="",C4=""),"",IFERROR(VLOOKUP(B4&"|||"&C4,MAESTRA!$A$3:$J$500,6,0),"⚠ No encontrado")) | F4: =IF(OR(B4="",C4=""),"",IFERROR(VLOOKUP(B4&"|||"&C4,MAESTRA!$A$3:$J$500,7,0),"⚠ No encontrado")) | G4: Otros Gastos CASA LIMPIA PLANILLA AC OTROS | H4: =IF(OR(B4="",C4=""),"",IFERROR(VLOOKUP(B4&"|||"&C4,MAESTRA!$A$3:$J$500,9,0),"")) | I4: NO PAGAR LEGALIZA PAGO POR PSE ASEO OFICINA CASALIMPIA BARRANQUILLA | J4: Barranquilla | K4: AP223365 | L4: 46028 | N4: 546400 | O4: 5 | P4: 46036 | R4: APROBACIÓN GERENCIA DE PERSONAS Y ADMÓN | T4: enero 2026
A5: 2 | B5: CASALIMPIA SA | D5: ADM | E5: =IF(OR(B5="",C5=""),"",IFERROR(VLOOKUP(B5&"|||"&C5,MAESTRA!$A$3:$J$500,6,0),"⚠ No encontrado")) | F5: =IF(OR(B5="",C5=""),"",IFERROR(VLOOKUP(B5&"|||"&C5,MAESTRA!$A$3:$J$500,7,0),"⚠ No encontrado")) | G5: Otros Gastos CASA LIMPIA PLANILLA AC OTROS | H5: =IF(OR(B5="",C5=""),"",IFERROR(VLOOKUP(B5&"|||"&C5,MAESTRA!$A$3:$J$500,9,0),"")) | I5: NO PAGAR LEGALIZA PAGO POR PSE ASEO OFICINA CASALIMPIA CALI | J5: Cali | K5: AP223364 | L5: 46028 | N5: 409800 | O5: 4 | P5: 46036 | R5: APROBACIÓN GERENCIA DE PERSONAS Y ADMÓN | T5: enero 2026
A6: 3 | B6: CAMARA DE COMERCIO DE BOGOTA | D6: ADM | E6: =IF(OR(B6="",C6=""),"",IFERROR(VLOOKUP(B6&"|||"&C6,MAESTRA!$A$3:$J$500,6,0),"⚠ No encontrado")) | F6: =IF(OR(B6="",C6=""),"",IFERROR(VLOOKUP(B6&"|||"&C6,MAESTRA!$A$3:$J$500,7,0),"⚠ No encontrado")) | G6: Trámites notariales autenticaciones | H6: =IF(OR(B6="",C6=""),"",IFERROR(VLOOKUP(B6&"|||"&C6,MAESTRA!$A$3:$J$500,9,0),"")) | I6: NO PAGAR LEGALIZA CAJA MENOR BOG COMPRA DE CAMARA Y COMERCIO | J6: Calle 100 | K6: TV439715239 | L6: 46024 | N6: 12100 | O6: 1920 | P6: 46036 | R6: APROBACIÓN GERENCIA DE PERSONAS Y ADMÓN | T6: enero 2026
A7: 4 | B7: GASEOSAS LUX S.A.S. | D7: ADM | E7: =IF(OR(B7="",C7=""),"",IFERROR(VLOOKUP(B7&"|||"&C7,MAESTRA!$A$3:$J$500,6,0),"⚠ No encontrado")) | F7: =IF(OR(B7="",C7=""),"",IFERROR(VLOOKUP(B7&"|||"&C7,MAESTRA!$A$3:$J$500,7,0),"⚠ No encontrado")) | G7: Material Copa/Cozinha | H7: =IF(OR(B7="",C7=""),"",IFERROR(VLOOKUP(B7&"|||"&C7,MAESTRA!$A$3:$J$500,9,0),"")) | I7: NO PAGAR LEGALIZA CAJA MENOR AEROPUERTO COMPRA 3 BOTELLONES DE AGUA | J7: Aeropuerto | K7: GL071180399 | L7: 46030 | N7: 40050 | R7: APROBACIÓN GERENCIA DE PERSONAS Y ADMÓN | T7: enero 2026
A8: 5 | B8: OSCAR ANTONIO HERNANDEZ GOMEZ | D8: ADM | E8: =IF(OR(B8="",C8=""),"",IFERROR(VLOOKUP(B8&"|||"&C8,MAESTRA!$A$3:$J$500,6,0),"⚠ No encontrado")) | F8: =IF(OR(B8="",C8=""),"",IFERROR(VLOOKUP(B8&"|||"&C8,MAESTRA!$A$3:$J$500,7,0),"⚠ No encontrado")) | G8: Trámites notariales autenticaciones | H8: =IF(OR(B8="",C8=""),"",IFERROR(VLOOKUP(B8&"|||"&C8,MAESTRA!$A$3:$J$500,9,0),"")) | I8: NO PAGAR LEGALIZA CAJA MENOR BOGOTA AUTENTICA CONTRATO PROVEEDOR OTM DIANA CASAS | J8: Calle 100 | K8: FEV140042 | L8: 46030 | N8: 4200 | O8: 1922 | P8: 46036 | R8: APROBACIÓN GERENCIA DE PERSONAS Y ADMÓN | T8: enero 2026
A9: 6 | B9: SUPERMARKET LA COLOMBIANA SAS ZOMAC | D9: ADM | E9: =IF(OR(B9="",C9=""),"",IFERROR(VLOOKUP(B9&"|||"&C9,MAESTRA!$A$3:$J$500,6,0),"⚠ No encontrado")) | F9: =IF(OR(B9="",C9=""),"",IFERROR(VLOOKUP(B9&"|||"&C9,MAESTRA!$A$3:$J$500,7,0),"⚠ No encontrado")) | G9: Material Copa/Cozinha | H9: =IF(OR(B9="",C9=""),"",IFERROR(VLOOKUP(B9&"|||"&C9,MAESTRA!$A$3:$J$500,9,0),"")) | I9: NO PAGAR LEGALIZA CAJA MENOR BUENAVENTURA COMPRA BOTELLON DE AGUA | J9: Buenaventura | K9: SMEF42506 | L9: 46031 | N9: 30000 | O9: 8 | P9: 46036 | R9: APROBACIÓN GERENCIA DE PERSONAS Y ADMÓN | T9: enero 2026
A10: 7 | B10: OSCAR ANTONIO HERNANDEZ GOMEZ | D10: ADM | E10: =IF(OR(B10="",C10=""),"",IFERROR(VLOOKUP(B10&"|||"&C10,MAESTRA!$A$3:$J$500,6,0),"⚠ No encontrado")) | F10: =IF(OR(B10="",C10=""),"",IFERROR(VLOOKUP(B10&"|||"&C10,MAESTRA!$A$3:$J$500,7,0),"⚠ No encontrado")) | G10: Trámites notariales autenticaciones | H10: =IF(OR(B10="",C10=""),"",IFERROR(VLOOKUP(B10&"|||"&C10,MAESTRA!$A$3:$J$500,9,0),"")) | I10: NO PAGAR LEGALIZA CAJA MENOR BOGOTA AUTENTICA CARTAS MAERSK SILVIA TRIANA | J10: Calle 100 | K10: FEV140166 | L10: 46031 | N10: 14137 | O10: 1926 | P10: 46036 | R10: APROBACIÓN GERENCIA DE PERSONAS Y ADMÓN | T10: enero 2026
A11: 8 | B11: COLOMBIANA DE COMERCIO S.A. | D11: GH | E11: =IF(OR(B11="",C11=""),"",IFERROR(VLOOKUP(B11&"|||"&C11,MAESTRA!$A$3:$J$500,6,0),"⚠ No encontrado")) | F11: =IF(OR(B11="",C11=""),"",IFERROR(VLOOKUP(B11&"|||"&C11,MAESTRA!$A$3:$J$500,7,0),"⚠ No encontrado")) | G11: Plan estratégico en enero 2025 | H11: =IF(OR(B11="",C11=""),"",IFERROR(VLOOKUP(B11&"|||"&C11,MAESTRA!$A$3:$J$500,9,0),"")) | I11: NO PAGAR LEGALIZA CAJA MENOR BOGOTA COMPRA VASOS Y PAPEL SANDWICH DESAYUNO HEAD | J11: Transversal | K11: X9222557543 | L11: 46034 | N11: 28700 | O11: 1928 | P11: 46036 | R11: APROBACIÓN GERENCIA DE PERSONAS Y ADMÓN | T11: enero 2026
A12: 9 | B12: CADENA COMERCIAL OXXO COLOMBIA S A S | D12: GH | E12: =IF(OR(B12="",C12=""),"",IFERROR(VLOOKUP(B12&"|||"&C12,MAESTRA!$A$3:$J$500,6,0),"⚠ No encontrado")) | F12: =IF(OR(B12="",C12=""),"",IFERROR(VLOOKUP(B12&"|||"&C12,MAESTRA!$A$3:$J$500,7,0),"⚠ No encontrado")) | G12: Plan estratégico en enero 2025 | H12: =IF(OR(B12="",C12=""),"",IFERROR(VLOOKUP(B12&"|||"&C12,MAESTRA!$A$3:$J$500,9,0),"")) | I12: NO PAGAR LEGALIZA TC 9994 COMPRA GASEOSA ALMUERZO REUNION HEAD | J12: Transversal | K12: 234C210864 | L12: 46035 | N12: 54400 | O12: 1929 | P12: 46036 | R12: APROBACIÓN GERENCIA DE PERSONAS Y ADMÓN | T12: enero 2026
A13: 10 | B13: COORSERPARK S.A.S | D13: GH | E13: =IF(OR(B13="",C13=""),"",IFERROR(VLOOKUP(B13&"|||"&C13,MAESTRA!$A$3:$J$500,6,0),"⚠ No encontrado")) | F13: =IF(OR(B13="",C13=""),"",IFERROR(VLOOKUP(B13&"|||"&C13,MAESTRA!$A$3:$J$500,7,0),"⚠ No encontrado")) | G13: Detalles en momentos especificos (Matrimonio, grados, fallecimientos) | H13: =IF(OR(B13="",C13=""),"",IFERROR(VLOOKUP(B13&"|||"&C13,MAESTRA!$A$3:$J$500,9,0),"")) | I13: NO PAGAR LEGALIZA TC 9994 ARREGLO FLORAL DIANA GRACIA | J13: Transversal | K13: SER312797 | L13: 46031 | N13: 250000 | O13: 5 | P13: 46036 | R13: APROBACIÓN GERENCIA DE PERSONAS Y ADMÓN | T13: enero 2026
A14: 11 | B14: CADENA COMERCIAL OXXO COLOMBIA S A S | D14: GH | E14: =IF(OR(B14="",C14=""),"",IFERROR(VLOOKUP(B14&"|||"&C14,MAESTRA!$A$3:$J$500,6,0),"⚠ No encontrado")) | F14: =IF(OR(B14="",C14=""),"",IFERROR(VLOOKUP(B14&"|||"&C14,MAESTRA!$A$3:$J$500,7,0),"⚠ No encontrado")) | G14: Plan estratégico en enero 2025 | H14: =IF(OR(B14="",C14=""),"",IFERROR(VLOOKUP(B14&"|||"&C14,MAESTRA!$A$3:$J$500,9,0),"")) | I14: NO PAGAR LEGALIZA TC 9994 COMPRA AGUA REUNION HEAD | J14: Transversal | K14: 334C240525 | L14: 46035 | N14: 81600 | O14: 1930 | P14: 46036 | R14: APROBACIÓN GERENCIA DE PERSONAS Y ADMÓN | T14: enero 2026
A15: 12 | B15: GRUPO CBC S.A.S. | D15: GH | E15: =IF(OR(B15="",C15=""),"",IFERROR(VLOOKUP(B15&"|||"&C15,MAESTRA!$A$3:$J$500,6,0),"⚠ No encontrado")) | F15: =IF(OR(B15="",C15=""),"",IFERROR(VLOOKUP(B15&"|||"&C15,MAESTRA!$A$3:$J$500,7,0),"⚠ No encontrado")) | G15: Café / Almuerzo con colaboradores | H15: =IF(OR(B15="",C15=""),"",IFERROR(VLOOKUP(B15&"|||"&C15,MAESTRA!$A$3:$J$500,9,0),"")) | I15: NO PAGAR LEGALIZA GINNA CASTRO ALMUERZO TRABAJO AURA,MARIANA,AACR | J15: Calle 100 | K15: A118120840 | L15: 46038 | N15: 186351 | O15: 7281 | P15: 46059 | R15: APROBACIÓN GERENCIA DE PERSONAS Y ADMÓN | T15: enero 2026
A16: 13 | B16: CADENA COMERCIAL OXXO COLOMBIA S A S | D16: GH | E16: =IF(OR(B16="",C16=""),"",IFERROR(VLOOKUP(B16&"|||"&C16,MAESTRA!$A$3:$J$500,6,0),"⚠ No encontrado")) | F16: =IF(OR(B16="",C16=""),"",IFERROR(VLOOKUP(B16&"|||"&C16,MAESTRA!$A$3:$J$500,7,0),"⚠ No encontrado")) | G16: Plan estratégico en enero 2025 | H16: =IF(OR(B16="",C16=""),"",IFERROR(VLOOKUP(B16&"|||"&C16,MAESTRA!$A$3:$J$500,9,0),"")) | I16: NO PAGAR LEGALIZA CAJA MENOR BOG COMPRA QUESOS REUNION VENTAS | J16: Transversal | K16: 334C243538 | L16: 46041 | N16: 34800 | O16: 7288 | P16: 46059 | R16: APROBACIÓN GERENCIA DE PERSONAS Y ADMÓN | T16: enero 2026
A17: 14 | B17: CADENA COMERCIAL OXXO COLOMBIA S A S | D17: GH | E17: =IF(OR(B17="",C17=""),"",IFERROR(VLOOKUP(B17&"|||"&C17,MAESTRA!$A$3:$J$500,6,0),"⚠ No encontrado")) | F17: =IF(OR(B17="",C17=""),"",IFERROR(VLOOKUP(B17&"|||"&C17,MAESTRA!$A$3:$J$500,7,0),"⚠ No encontrado")) | G17: Plan estratégico en enero 2025 | H17: =IF(OR(B17="",C17=""),"",IFERROR(VLOOKUP(B17&"|||"&C17,MAESTRA!$A$3:$J$500,9,0),"")) | I17: NO PAGAR LEGALIZA CAJA MENOR BOG COMPRA AGUAS REUNION VENTAS | J17: Transversal | K17: 234C212340 | L17: 46041 | N17: 41400 | O17: 7289 | P17: 46059 | R17: APROBACIÓN GERENCIA DE PERSONAS Y ADMÓN | T17: enero 2026
A18: 15 | B18: SUPERMARKET LA COLOMBIANA SAS ZOMAC | D18: ADM | E18: =IF(OR(B18="",C18=""),"",IFERROR(VLOOKUP(B18&"|||"&C18,MAESTRA!$A$3:$J$500,6,0),"⚠ No encontrado")) | F18: =IF(OR(B18="",C18=""),"",IFERROR(VLOOKUP(B18&"|||"&C18,MAESTRA!$A$3:$J$500,7,0),"⚠ No encontrado")) | G18: Comidas de trabajo extra colaboradores | H18: =IF(OR(B18="",C18=""),"",IFERROR(VLOOKUP(B18&"|||"&C18,MAESTRA!$A$3:$J$500,9,0),"")) | I18: NO PAGAR LEGALIZA CAJA MENOR BUENAVENTURA COMPRA GASEOSA | J18: Buenaventura | K18: SMEF43854 | L18: 46038 | N18: 10500 | O18: 25 | P18: 46059 | R18: APROBACIÓN GERENCIA DE PERSONAS Y ADMÓN | T18: enero 2026
A19: 16 | B19: ALMACENES ÉXITO S.A | D19: ADM | E19: =IF(OR(B19="",C19=""),"",IFERROR(VLOOKUP(B19&"|||"&C19,MAESTRA!$A$3:$J$500,6,0),"⚠ No encontrado")) | F19: =IF(OR(B19="",C19=""),"",IFERROR(VLOOKUP(B19&"|||"&C19,MAESTRA!$A$3:$J$500,7,0),"⚠ No encontrado")) | G19: Material Copa/Cozinha | H19: =IF(OR(B19="",C19=""),"",IFERROR(VLOOKUP(B19&"|||"&C19,MAESTRA!$A$3:$J$500,9,0),"")) | I19: NO PAGAR LEGALIZA NADIA MARTINEZ COMPRA ELEMENTOS ASEO SUCURSAL BARRANQUILLLA | J19: Barranquilla | K19: VF2711438 | L19: 46035 | N19: 251472 | O19: 7 | P19: 46051 | R19: APROBACIÓN GERENCIA DE PERSONAS Y ADMÓN | T19: enero 2026
A20: 17 | B20: GASEOSAS LUX S.A.S. | D20: ADM | E20: =IF(OR(B20="",C20=""),"",IFERROR(VLOOKUP(B20&"|||"&C20,MAESTRA!$A$3:$J$500,6,0),"⚠ No encontrado")) | F20: =IF(OR(B20="",C20=""),"",IFERROR(VLOOKUP(B20&"|||"&C20,MAESTRA!$A$3:$J$500,7,0),"⚠ No encontrado")) | G20: Material Copa/Cozinha | H20: =IF(OR(B20="",C20=""),"",IFERROR(VLOOKUP(B20&"|||"&C20,MAESTRA!$A$3:$J$500,9,0),"")) | I20: NO PAGAR LEGALIZA CAJA MENOR AEROPUERTO COMPRA BOTELLONES DE AGUA | J20: Aeropuerto | K20: GL071228596 | L20: 46043 | N20: 40050 | R20: APROBACIÓN GERENCIA DE PERSONAS Y ADMÓN | T20: enero 2026
A21: 18 | B21: COMIDAS VARPEL SAS | D21: GH | E21: =IF(OR(B21="",C21=""),"",IFERROR(VLOOKUP(B21&"|||"&C21,MAESTRA!$A$3:$J$500,6,0),"⚠ No encontrado")) | F21: =IF(OR(B21="",C21=""),"",IFERROR(VLOOKUP(B21&"|||"&C21,MAESTRA!$A$3:$J$500,7,0),"⚠ No encontrado")) | G21: Plan estratégico en enero 2025 | H21: =IF(OR(B21="",C21=""),"",IFERROR(VLOOKUP(B21&"|||"&C21,MAESTRA!$A$3:$J$500,9,0),"")) | I21: NO PAGAR LEGALIZA TC BB 9994 ALMUERZO REUNION HEAD 2 | J21: Transversal | K21: E07A67636 | L21: 46048 | N21: 615000 | O21: 7294 | P21: 46059 | R21: APROBACIÓN GERENCIA DE PERSONAS Y ADMÓN | T21: enero 2026
A22: 19 | B22: SUPERMARKET LA COLOMBIANA SAS ZOMAC | D22: ADM | E22: =IF(OR(B22="",C22=""),"",IFERROR(VLOOKUP(B22&"|||"&C22,MAESTRA!$A$3:$J$500,6,0),"⚠ No encontrado")) | F22: =IF(OR(B22="",C22=""),"",IFERROR(VLOOKUP(B22&"|||"&C22,MAESTRA!$A$3:$J$500,7,0),"⚠ No encontrado")) | G22: Material Copa/Cozinha | H22: =IF(OR(B22="",C22=""),"",IFERROR(VLOOKUP(B22&"|||"&C22,MAESTRA!$A$3:$J$500,9,0),"")) | I22: NO PAGAR LEGALIZA CAJA MENOR BUENAVENTURA COMPRA BOTELLONES DE AGUA | J22: Buenaventura | K22: SMEF45396 | L22: 46048 | N22: 30000 | O22: 26 | P22: 46059 | R22: APROBACIÓN GERENCIA DE PERSONAS Y ADMÓN | T22: enero 2026
A23: 20 | B23: COMIDAS VARPEL SAS | D23: GH | E23: =IF(OR(B23="",C23=""),"",IFERROR(VLOOKUP(B23&"|||"&C23,MAESTRA!$A$3:$J$500,6,0),"⚠ No encontrado")) | F23: =IF(OR(B23="",C23=""),"",IFERROR(VLOOKUP(B23&"|||"&C23,MAESTRA!$A$3:$J$500,7,0),"⚠ No encontrado")) | G23: Plan estratégico en enero 2025 | H23: =IF(OR(B23="",C23=""),"",IFERROR(VLOOKUP(B23&"|||"&C23,MAESTRA!$A$3:$J$500,9,0),"")) | I23: NO PAGAR LEGALIZA TC 9994 COMPRA ALMUERZO REUNION VENTAS CON AACR | J23: Transversal | K23: E07A65981 | L23: 46041 | N23: 388200 | O23: 7303 | P23: 46059 | R23: APROBACIÓN GERENCIA DE PERSONAS Y ADMÓN | T23: enero 2026
A24: 21 | B24: LISDEY MARYORY CARDONA OSPINA | D24: ADM | E24: =IF(OR(B24="",C24=""),"",IFERROR(VLOOKUP(B24&"|||"&C24,MAESTRA!$A$3:$J$500,6,0),"⚠ No encontrado")) | F24: =IF(OR(B24="",C24=""),"",IFERROR(VLOOKUP(B24&"|||"&C24,MAESTRA!$A$3:$J$500,7,0),"⚠ No encontrado")) | G24: Material Copa/Cozinha | H24: =IF(OR(B24="",C24=""),"",IFERROR(VLOOKUP(B24&"|||"&C24,MAESTRA!$A$3:$J$500,9,0),"")) | I24: NO PAGAR LEGALIZA CAJA MENOR CARTGENA COMPRA BOTELLONES DE AGUA | J24: Cartagena | K24: FELM31652 | L24: 46043 | N24: 18000 | O24: 36 | P24: 46059 | R24: APROBACIÓN GERENCIA DE PERSONAS Y ADMÓN | T24: enero 2026
A25: 22 | B25: GRUPO CBC S.A.S. | D25: GH | E25: =IF(OR(B25="",C25=""),"",IFERROR(VLOOKUP(B25&"|||"&C25,MAESTRA!$A$3:$J$500,6,0),"⚠ No encontrado")) | F25: =IF(OR(B25="",C25=""),"",IFERROR(VLOOKUP(B25&"|||"&C25,MAESTRA!$A$3:$J$500,7,0),"⚠ No encontrado")) | G25: Café / Almuerzo con colaboradores | H25: =IF(OR(B25="",C25=""),"",IFERROR(VLOOKUP(B25&"|||"&C25,MAESTRA!$A$3:$J$500,9,0),"")) | I25: NO PAGAR LEGALIZA TC 9994 ALMUERZO DE TRABAJO AREA ADMITIVA CAMBIO PISO OF | J25: Calle 100 | K25: A22326458 | L25: 46045 | N25: 314100 | O25: 7310 | P25: 46059 | R25: APROBACIÓN GERENCIA DE PERSONAS Y ADMÓN | T25: enero 2026
A26: 23 | B26: AMERICAN LOCKS CENTER SAS | D26: ADM | E26: =IF(OR(B26="",C26=""),"",IFERROR(VLOOKUP(B26&"|||"&C26,MAESTRA!$A$3:$J$500,6,0),"⚠ No encontrado")) | F26: =IF(OR(B26="",C26=""),"",IFERROR(VLOOKUP(B26&"|||"&C26,MAESTRA!$A$3:$J$500,7,0),"⚠ No encontrado")) | G26: Material De Escritorio | H26: =IF(OR(B26="",C26=""),"",IFERROR(VLOOKUP(B26&"|||"&C26,MAESTRA!$A$3:$J$500,9,0),"")) | I26: NO PAGAR LEGALIZA TC 9994 COMPRA 3 ROLLOS VINIPEL PARA SILLAS DE OF | J26: Calle 100 | K26: FE63145 | L26: 46045 | N26: 105000 | O26: 7319 | P26: 46059 | R26: APROBACIÓN GERENCIA DE PERSONAS Y ADMÓN | T26: enero 2026
A27: 24 | B27: LISDEY MARYORY CARDONA OSPINA | D27: ADM | E27: =IF(OR(B27="",C27=""),"",IFERROR(VLOOKUP(B27&"|||"&C27,MAESTRA!$A$3:$J$500,6,0),"⚠ No encontrado")) | F27: =IF(OR(B27="",C27=""),"",IFERROR(VLOOKUP(B27&"|||"&C27,MAESTRA!$A$3:$J$500,7,0),"⚠ No encontrado")) | G27: Material Copa/Cozinha | H27: =IF(OR(B27="",C27=""),"",IFERROR(VLOOKUP(B27&"|||"&C27,MAESTRA!$A$3:$J$500,9,0),"")) | I27: NO PAGAR LEGALIZA CAJA MENOR CARTGENA COMPRA BOTELLONES DE AGUA | J27: Cartagena | K27: FELM31912 | L27: 46048 | N27: 18000 | O27: 37 | P27: 46059 | R27: APROBACIÓN GERENCIA DE PERSONAS Y ADMÓN | T27: enero 2026
A28: 25 | B28: CREPES Y WAFFLES S A | D28: GH | E28: =IF(OR(B28="",C28=""),"",IFERROR(VLOOKUP(B28&"|||"&C28,MAESTRA!$A$3:$J$500,6,0),"⚠ No encontrado")) | F28: =IF(OR(B28="",C28=""),"",IFERROR(VLOOKUP(B28&"|||"&C28,MAESTRA!$A$3:$J$500,7,0),"⚠ No encontrado")) | G28: Plan estratégico en enero 2025 | H28: =IF(OR(B28="",C28=""),"",IFERROR(VLOOKUP(B28&"|||"&C28,MAESTRA!$A$3:$J$500,9,0),"")) | I28: NO PAGAR LEGALIZA CAJA MENOR BOGOTA ALMUERZO ACCR REUNION HEAD 2 | J28: Calle 100 | K28: R06E462207 | L28: 46048 | N28: 47900 | O28: 7333 | P28: 46059 | R28: APROBACIÓN GERENCIA DE PERSONAS Y ADMÓN | T28: enero 2026
A29: 26 | B29: JOHAN DANIEL ESTUPIAN CARDENAS | D29: ADM | E29: =IF(OR(B29="",C29=""),"",IFERROR(VLOOKUP(B29&"|||"&C29,MAESTRA!$A$3:$J$500,6,0),"⚠ No encontrado")) | F29: =IF(OR(B29="",C29=""),"",IFERROR(VLOOKUP(B29&"|||"&C29,MAESTRA!$A$3:$J$500,7,0),"⚠ No encontrado")) | G29: Conservacion Y Manutenimiento De Oficina | H29: =IF(OR(B29="",C29=""),"",IFERROR(VLOOKUP(B29&"|||"&C29,MAESTRA!$A$3:$J$500,9,0),"")) | I29: NO PAGAR LEGALIZA CAJA MENOR BUENAVENTURA COMPRA CHAPA PUERTA BAÑO | J29: Buenaventura | K29: FAC1937 | L29: 46049 | N29: 80000 | O29: 27 | P29: 46059 | R29: APROBACIÓN GERENCIA DE PERSONAS Y ADMÓN | T29: enero 2026
A30: 27 | B30: PRODUCTOS PARA EL ALMA SAS | D30: ADM | E30: =IF(OR(B30="",C30=""),"",IFERROR(VLOOKUP(B30&"|||"&C30,MAESTRA!$A$3:$J$500,6,0),"⚠ No encontrado")) | F30: =IF(OR(B30="",C30=""),"",IFERROR(VLOOKUP(B30&"|||"&C30,MAESTRA!$A$3:$J$500,7,0),"⚠ No encontrado")) | G30: Reuniones gerenciales CEM (Comida) | H30: =IF(OR(B30="",C30=""),"",IFERROR(VLOOKUP(B30&"|||"&C30,MAESTRA!$A$3:$J$500,9,0),"")) | I30: NO PAGAR LEGALIZA TC 9994 DESAYUNO CEM DE ENERO | J30: Calle 100 | K30: FEJC24141 | L30: 46050 | N30: 112000 | O30: 7340 | P30: 46059 | R30: APROBACIÓN GERENCIA DE PERSONAS Y ADMÓN | T30: enero 2026
A31: 28 | B31: FIT CHOICES COMPANY S.A.S | D31: ADM | E31: =IF(OR(B31="",C31=""),"",IFERROR(VLOOKUP(B31&"|||"&C31,MAESTRA!$A$3:$J$500,6,0),"⚠ No encontrado")) | F31: =IF(OR(B31="",C31=""),"",IFERROR(VLOOKUP(B31&"|||"&C31,MAESTRA!$A$3:$J$500,7,0),"⚠ No encontrado")) | G31: Gastos De Representacion | H31: =IF(OR(B31="",C31=""),"",IFERROR(VLOOKUP(B31&"|||"&C31,MAESTRA!$A$3:$J$500,9,0),"")) | I31: NO PAGAR LEGALIZA NADIA MARTINEZ DESAYUNO CLIENTE ANDES | J31: Barranquilla | K31: FIT57997 | L31: 46044 | N31: 119800 | O31: 8 | P31: 46051 | R31: APROBACIÓN GERENCIA DE PERSONAS Y ADMÓN | T31: enero 2026
A32: 29 | B32: CASALIMPIA SA | D32: ADM | E32: =IF(OR(B32="",C32=""),"",IFERROR(VLOOKUP(B32&"|||"&C32,MAESTRA!$A$3:$J$500,6,0),"⚠ No encontrado")) | F32: =IF(OR(B32="",C32=""),"",IFERROR(VLOOKUP(B32&"|||"&C32,MAESTRA!$A$3:$J$500,7,0),"⚠ No encontrado")) | G32: Otros Gastos CASA LIMPIA PLANILLA AC OTROS | H32: =IF(OR(B32="",C32=""),"",IFERROR(VLOOKUP(B32&"|||"&C32,MAESTRA!$A$3:$J$500,9,0),"")) | I32: NO PAGAR LEGALIZA TC 9994 ASEO OFICINA CRAFT BARRANQUILLA | J32: Barranquilla | K32: AP225405 | L32: 46052 | N32: 491760 | O32: 9 | P32: 46059 | R32: APROBACIÓN GERENCIA DE PERSONAS Y ADMÓN | T32: enero 2026
... A38: 35 | B38: BAGATELLE S.A.S. | D38: ADM | E38: =IF(OR(B38="",C38=""),"",IFERROR(VLOOKUP(B38&"|||"&C38,MAESTRA!$A$3:$J$500,6,0),"⚠ No encontrado")) | F38: =IF(OR(B38="",C38=""),"",IFERROR(VLOOKUP(B38&"|||"&C38,MAESTRA!$A$3:$J$500,7,0),"⚠ No encontrado")) | G38: Gastos De Representacion | H38: =IF(OR(B38="",C38=""),"",IFERROR(VLOOKUP(B38&"|||"&C38,MAESTRA!$A$3:$J$500,9,0),"")) | I38: NO PAGAR LEGALIZA TC 0206 DESAYUNO CLIENTE MSL CON AACR | J38: Calle 100 | K38: B2198377 | L38: 46041 | N38: 182659 | O38: 7367 | P38: 46059 | R38: APROBACIÓN GERENCIA DE PERSONAS Y ADMÓN | T38: enero 2026
A39: 36 | B39: SEGUROS BOLIVAR | D39: GH | E39: =IF(OR(B39="",C39=""),"",IFERROR(VLOOKUP(B39&"|||"&C39,MAESTRA!$A$3:$J$500,6,0),"⚠ No encontrado")) | F39: =IF(OR(B39="",C39=""),"",IFERROR(VLOOKUP(B39&"|||"&C39,MAESTRA!$A$3:$J$500,7,0),"⚠ No encontrado")) | G39: =IF(OR(B39="",C39=""),"",IFERROR(VLOOKUP(B39&"|||"&C39,MAESTRA!$A$3:$J$500,8,0),"⚠ No encontrado")) | H39: =IF(OR(B39="",C39=""),"",IFERROR(VLOOKUP(B39&"|||"&C39,MAESTRA!$A$3:$J$500,9,0),"")) | I39: NO PAGAR FACTURA APORTES REALIZADOS A ARL AÑO 2025 | J39: Calle 100 | K39: POL15783488 | L39: 46037 | N39: 10586700 | R39: APROBACIÓN GERENCIA DE PERSONAS Y ADMÓN | T39: enero 2026
A40: 37 | B40: PANAMERICANA LIBRERÍA Y PAPELERÍA S.A. | D40: IT | E40: =IF(OR(B40="",C40=""),"",IFERROR(VLOOKUP(B40&"|||"&C40,MAESTRA!$A$3:$J$500,6,0),"⚠ No encontrado")) | F40: =IF(OR(B40="",C40=""),"",IFERROR(VLOOKUP(B40&"|||"&C40,MAESTRA!$A$3:$J$500,7,0),"⚠ No encontrado")) | G40: Insumos y perifericos | H40: =IF(OR(B40="",C40=""),"",IFERROR(VLOOKUP(B40&"|||"&C40,MAESTRA!$A$3:$J$500,9,0),"")) | I40: NO PAGAR LEGALIZA CAJA MENOR CTG COMPRA MOUSE Y TECLADO OF CTG | J40: Cartagena | K40: 29E732573 | L40: 46043 | N40: 79900 | O40: 38 | P40: 46059 | R40: APROBACIÓN GERENCIA DE PERSONAS Y ADMÓN | T40: enero 2026
A41: 38 | B41: CREPES Y WAFFLES S A | D41: GH | E41: =IF(OR(B41="",C41=""),"",IFERROR(VLOOKUP(B41&"|||"&C41,MAESTRA!$A$3:$J$500,6,0),"⚠ No encontrado")) | F41: =IF(OR(B41="",C41=""),"",IFERROR(VLOOKUP(B41&"|||"&C41,MAESTRA!$A$3:$J$500,7,0),"⚠ No encontrado")) | G41: Cumpleaños | H41: =IF(OR(B41="",C41=""),"",IFERROR(VLOOKUP(B41&"|||"&C41,MAESTRA!$A$3:$J$500,9,0),"")) | I41: NO PAGAR LEGALIZA MARIANA MUNAR, HELADOS DE CUMPLEAÑOS MARIANA SOTELO, SOFIA TORRES Y EDWIN RAMIREZ | J41: Transversal | K41: R06E466439 | L41: 46057 | N41: 49100 | O41: 2001 | P41: 46065 | R41: APROBACIÓN GERENCIA DE PERSONAS Y ADMÓN | T41: febrero 2026
A42: 39 | B42: CADENA COMERCIAL OXXO COLOMBIA S A S | D42: ADM | E42: =IF(OR(B42="",C42=""),"",IFERROR(VLOOKUP(B42&"|||"&C42,MAESTRA!$A$3:$J$500,6,0),"⚠ No encontrado")) | F42: =IF(OR(B42="",C42=""),"",IFERROR(VLOOKUP(B42&"|||"&C42,MAESTRA!$A$3:$J$500,7,0),"⚠ No encontrado")) | G42: Reuniones gerenciales CEM (Comida) | H42: =IF(OR(B42="",C42=""),"",IFERROR(VLOOKUP(B42&"|||"&C42,MAESTRA!$A$3:$J$500,9,0),"")) | I42: NO PAGAR LEGALIZA CAJA MENOR BOGOTA COMPRA AGUA CEM | J42: Transversal | K42: 334C247688 | L42: 46050 | N42: 13600 | O42: 7364 | P42: 46059 | R42: APROBACIÓN GERENCIA DE PERSONAS Y ADMÓN | T42: enero 2026
A43: 40 | B43: GASEOSAS LUX S.A.S. | D43: ADM | E43: =IF(OR(B43="",C43=""),"",IFERROR(VLOOKUP(B43&"|||"&C43,MAESTRA!$A$3:$J$500,6,0),"⚠ No encontrado")) | F43: =IF(OR(B43="",C43=""),"",IFERROR(VLOOKUP(B43&"|||"&C43,MAESTRA!$A$3:$J$500,7,0),"⚠ No encontrado")) | G43: Material Copa/Cozinha | H43: =IF(OR(B43="",C43=""),"",IFERROR(VLOOKUP(B43&"|||"&C43,MAESTRA!$A$3:$J$500,9,0),"")) | I43: NO PAGAR LEGALIZA CAJA MENOR AEROPUERTO COMPRA 2 BOTELLONES DE AGUA | J43: Aeropuerto | K43: GL071282956 | L43: 46058 | N43: 26700 | R43: APROBACIÓN GERENCIA DE PERSONAS Y ADMÓN | T43: febrero 2026
A44: 41 | B44: CAMARA DE COMERCIO DE BOGOTA | D44: ADM | E44: =IF(OR(B44="",C44=""),"",IFERROR(VLOOKUP(B44&"|||"&C44,MAESTRA!$A$3:$J$500,6,0),"⚠ No encontrado")) | F44: =IF(OR(B44="",C44=""),"",IFERROR(VLOOKUP(B44&"|||"&C44,MAESTRA!$A$3:$J$500,7,0),"⚠ No encontrado")) | G44: Trámites notariales autenticaciones | H44: =IF(OR(B44="",C44=""),"",IFERROR(VLOOKUP(B44&"|||"&C44,MAESTRA!$A$3:$J$500,9,0),"")) | I44: NO PAGAR LEGALIZA CAJA MENOR BOGOTA COMPRA CERTIFICADO CMRA CIO CRAFT | J44: Calle 100 | K44: TV439865226 | L44: 46057 | N44: 12100 | O44: 2004 | P44: 46065 | R44: APROBACIÓN GERENCIA DE PERSONAS Y ADMÓN | T44: febrero 2026
A45: 42 | B45: SUPERMARKET LA COLOMBIANA SAS ZOMAC | D45: ADM | E45: =IF(OR(B45="",C45=""),"",IFERROR(VLOOKUP(B45&"|||"&C45,MAESTRA!$A$3:$J$500,6,0),"⚠ No encontrado")) | F45: =IF(OR(B45="",C45=""),"",IFERROR(VLOOKUP(B45&"|||"&C45,MAESTRA!$A$3:$J$500,7,0),"⚠ No encontrado")) | G45: Material Copa/Cozinha | H45: =IF(OR(B45="",C45=""),"",IFERROR(VLOOKUP(B45&"|||"&C45,MAESTRA!$A$3:$J$500,9,0),"")) | I45: NO PAGAR LEGALIZA CAJA MENOR BUENAVENTURA COMPRA BOTELLON DE AGUA | J45: Buenaventura | K45: SMEF46966 | L45: 46059 | N45: 30000 | O45: 13 | P45: 46065 | R45: APROBACIÓN GERENCIA DE PERSONAS Y ADMÓN | T45: febrero 2026
A46: 43 | B46: ALMACENES ÉXITO S.A | D46: ADM | E46: =IF(OR(B46="",C46=""),"",IFERROR(VLOOKUP(B46&"|||"&C46,MAESTRA!$A$3:$J$500,6,0),"⚠ No encontrado")) | F46: =IF(OR(B46="",C46=""),"",IFERROR(VLOOKUP(B46&"|||"&C46,MAESTRA!$A$3:$J$500,7,0),"⚠ No encontrado")) | G46: Regalos clientes | H46: =IF(OR(B46="",C46=""),"",IFERROR(VLOOKUP(B46&"|||"&C46,MAESTRA!$A$3:$J$500,9,0),"")) | I46: NO PAGAR LEGLIZA NADIA MARTINEZ COMPRA CUPCAKES ATENDER CLIENTE M&S Logistics Trading Solutions | J46: Barranquilla | K46: VF3127169 | L46: 46055 | N46: 41400 | O46: 5 | P46: 46065 | R46: APROBACIÓN GERENCIA DE PERSONAS Y ADMÓN | T46: febrero 2026
A47: 44 | B47: HOT AMERICAS FAVORITE PIZZA SAS | D47: ADM | E47: =IF(OR(B47="",C47=""),"",IFERROR(VLOOKUP(B47&"|||"&C47,MAESTRA!$A$3:$J$500,6,0),"⚠ No encontrado")) | F47: =IF(OR(B47="",C47=""),"",IFERROR(VLOOKUP(B47&"|||"&C47,MAESTRA!$A$3:$J$500,7,0),"⚠ No encontrado")) | G47: Gastos De Representacion | H47: =IF(OR(B47="",C47=""),"",IFERROR(VLOOKUP(B47&"|||"&C47,MAESTRA!$A$3:$J$500,9,0),"")) | I47: NO PAGAR LEGALIZA NADIA MARTINEZ ALMUERZO CLIENTE MASTELINE | J47: Barranquilla | K47: EMAL32923 | L47: 46058 | N47: 168587 | O47: 6 | P47: 46065 | R47: APROBACIÓN GERENCIA DE PERSONAS Y ADMÓN | T47: febrero 2026
A48: 45 | B48: DLK S.A.S | D48: ADM | E48: =IF(OR(B48="",C48=""),"",IFERROR(VLOOKUP(B48&"|||"&C48,MAESTRA!$A$3:$J$500,6,0),"⚠ No encontrado")) | F48: =IF(OR(B48="",C48=""),"",IFERROR(VLOOKUP(B48&"|||"&C48,MAESTRA!$A$3:$J$500,7,0),"⚠ No encontrado")) | G48: Gastos De Representacion | H48: =IF(OR(B48="",C48=""),"",IFERROR(VLOOKUP(B48&"|||"&C48,MAESTRA!$A$3:$J$500,9,0),"")) | I48: NO PAGAR LEGALIZA NADIA MARTINEZ ALMUERZO CLIENTE ALONSO | J48: Barranquilla | K48: FPAT2535 | L48: 46063 | N48: 198196.25 | O48: 2050 | P48: 46065 | R48: APROBACIÓN GERENCIA DE PERSONAS Y ADMÓN | T48: febrero 2026
A49: 46 | B49: CREPES Y WAFFLES S A | D49: GH | E49: =IF(OR(B49="",C49=""),"",IFERROR(VLOOKUP(B49&"|||"&C49,MAESTRA!$A$3:$J$500,6,0),"⚠ No encontrado")) | F49: =IF(OR(B49="",C49=""),"",IFERROR(VLOOKUP(B49&"|||"&C49,MAESTRA!$A$3:$J$500,7,0),"⚠ No encontrado")) | G49: Cumpleaños | H49: =IF(OR(B49="",C49=""),"",IFERROR(VLOOKUP(B49&"|||"&C49,MAESTRA!$A$3:$J$500,9,0),"")) | I49: NO PAGAR LEGALIZA CAJA MENOR BOGOTA COMPRA POSTRE CUMPLE MARIA,DANIEL Y MARIANA | J49: Transversal | K49: R06E469026 | L49: 46063 | N49: 45000 | O49: 5083 | P49: 46079 | R49: APROBACIÓN GERENCIA DE PERSONAS Y ADMÓN | T49: febrero 2026
A50: 47 | B50: LISDEY MARYORY CARDONA OSPINA | D50: ADM | E50: =IF(OR(B50="",C50=""),"",IFERROR(VLOOKUP(B50&"|||"&C50,MAESTRA!$A$3:$J$500,6,0),"⚠ No encontrado")) | F50: =IF(OR(B50="",C50=""),"",IFERROR(VLOOKUP(B50&"|||"&C50,MAESTRA!$A$3:$J$500,7,0),"⚠ No encontrado")) | G50: Material Copa/Cozinha | H50: =IF(OR(B50="",C50=""),"",IFERROR(VLOOKUP(B50&"|||"&C50,MAESTRA!$A$3:$J$500,9,0),"")) | I50: NO PAGAR LEGALIZA CAJA MENOR CARTAGENA COMPRA BOTELLON DE AGUA | J50: Cartagena | K50: FELM32742 | L50: 46064 | N50: 18000 | O50: 27 | P50: 46079 | R50: APROBACIÓN GERENCIA DE PERSONAS Y ADMÓN | T50: febrero 2026
A51: 48 | B51: PAN PA YA LTDA | D51: GH | E51: =IF(OR(B51="",C51=""),"",IFERROR(VLOOKUP(B51&"|||"&C51,MAESTRA!$A$3:$J$500,6,0),"⚠ No encontrado")) | F51: =IF(OR(B51="",C51=""),"",IFERROR(VLOOKUP(B51&"|||"&C51,MAESTRA!$A$3:$J$500,7,0),"⚠ No encontrado")) | G51: Café / Almuerzo con colaboradores | H51: =IF(OR(B51="",C51=""),"",IFERROR(VLOOKUP(B51&"|||"&C51,MAESTRA!$A$3:$J$500,9,0),"")) | I51: NO PAGAR LEGALIZA CAJA MENOR BOGOTA COMPRA REFRIGERIO COLABORADORES CALLE 100 | J51: Calle 100 | K51: 96C85806 | L51: 46065 | N51: 234000 | O51: 5088 | P51: 46079 | R51: APROBACIÓN GERENCIA DE PERSONAS Y ADMÓN | T51: febrero 2026
A52: 49 | B52: CADENA COMERCIAL OXXO COLOMBIA S A S | D52: GH | E52: =IF(OR(B52="",C52=""),"",IFERROR(VLOOKUP(B52&"|||"&C52,MAESTRA!$A$3:$J$500,6,0),"⚠ No encontrado")) | F52: =IF(OR(B52="",C52=""),"",IFERROR(VLOOKUP(B52&"|||"&C52,MAESTRA!$A$3:$J$500,7,0),"⚠ No encontrado")) | G52: Plan estratégico en enero 2025 | H52: =IF(OR(B52="",C52=""),"",IFERROR(VLOOKUP(B52&"|||"&C52,MAESTRA!$A$3:$J$500,9,0),"")) | I52: NO PAGAR LEGALIZA GINNA CASTRO TARJETA PEOPLE PASS COMPRA DESAYUNO REUNION COMERCIAL | J52: Calle 100 | K52: 234C219469 | L52: 46062 | N52: 9400 | O52: 5090 | P52: 46079 | R52: APROBACIÓN GERENCIA DE PERSONAS Y ADMÓN | T52: febrero 2026
A53: 50 | B53: CADENA COMERCIAL OXXO COLOMBIA S A S | D53: GH | E53: =IF(OR(B53="",C53=""),"",IFERROR(VLOOKUP(B53&"|||"&C53,MAESTRA!$A$3:$J$500,6,0),"⚠ No encontrado")) | F53: =IF(OR(B53="",C53=""),"",IFERROR(VLOOKUP(B53&"|||"&C53,MAESTRA!$A$3:$J$500,7,0),"⚠ No encontrado")) | G53: Plan estratégico en enero 2025 | H53: =IF(OR(B53="",C53=""),"",IFERROR(VLOOKUP(B53&"|||"&C53,MAESTRA!$A$3:$J$500,9,0),"")) | I53: NO PAGAR LEGALIZA GINNA CASTRO TARJETA PEOPLE PASS COMPRA DESAYUNO REUNION COMERCIAL | J53: Calle 100 | K53: 234C219465 | L53: 46062 | N53: 53100 | O53: 5092 | P53: 46079 | R53: APROBACIÓN GERENCIA DE PERSONAS Y ADMÓN | T53: febrero 2026
A54: 51 | B54: CADENA COMERCIAL OXXO COLOMBIA S A S | D54: GH | E54: =IF(OR(B54="",C54=""),"",IFERROR(VLOOKUP(B54&"|||"&C54,MAESTRA!$A$3:$J$500,6,0),"⚠ No encontrado")) | F54: =IF(OR(B54="",C54=""),"",IFERROR(VLOOKUP(B54&"|||"&C54,MAESTRA!$A$3:$J$500,7,0),"⚠ No encontrado")) | G54: Cumpleaños | H54: =IF(OR(B54="",C54=""),"",IFERROR(VLOOKUP(B54&"|||"&C54,MAESTRA!$A$3:$J$500,9,0),"")) | I54: NO PAGAR LEGALIZA CAJA MENOR BOGOTA COMPRA DESECHABLES CUMPLE AACR | J54: Calle 100 | K54: 234C221941 | L54: 46069 | N54: 20500 | O54: 5094 | P54: 46079 | R54: APROBACIÓN GERENCIA DE PERSONAS Y ADMÓN | T54: febrero 2026
A55: 52 | B55: BBI COLOMBIA S A S | D55: ADM | E55: =IF(OR(B55="",C55=""),"",IFERROR(VLOOKUP(B55&"|||"&C55,MAESTRA!$A$3:$J$500,6,0),"⚠ No encontrado")) | F55: =IF(OR(B55="",C55=""),"",IFERROR(VLOOKUP(B55&"|||"&C55,MAESTRA!$A$3:$J$500,7,0),"⚠ No encontrado")) | G55: Reuniones gerenciales CEM (Comida) | H55: =IF(OR(B55="",C55=""),"",IFERROR(VLOOKUP(B55&"|||"&C55,MAESTRA!$A$3:$J$500,9,0),"")) | I55: NO PAGAR LEGALIZA RAFAEL DE SA TARJETA PEOPLE PASS COMPRA DESAYUNO CEM | J55: Calle 100 | K55: 074B67288 | L55: 46071 | N55: 151300 | O55: 5177 | P55: 46079 | R55: APROBACIÓN GERENCIA DE PERSONAS Y ADMÓN | T55: febrero 2026
... A57: 54 | B57: BBI COLOMBIA S A S | D57: ADM | E57: =IF(OR(B57="",C57=""),"",IFERROR(VLOOKUP(B57&"|||"&C57,MAESTRA!$A$3:$J$500,6,0),"⚠ No encontrado")) | F57: =IF(OR(B57="",C57=""),"",IFERROR(VLOOKUP(B57&"|||"&C57,MAESTRA!$A$3:$J$500,7,0),"⚠ No encontrado")) | G57: Gastos De Representacion | H57: =IF(OR(B57="",C57=""),"",IFERROR(VLOOKUP(B57&"|||"&C57,MAESTRA!$A$3:$J$500,9,0),"")) | I57: NO PAGAR LEGALIZA RAFAEL DE SA TARJETA PEOPLE PASS ATENCION PROVEEDOR BANCO | J57: Calle 100 | K57: 073B23799 | L57: 46071 | N57: 10000 | O57: 5189 | P57: 46079 | R57: APROBACIÓN GERENCIA DE PERSONAS Y ADMÓN | T57: febrero 2026
A58: 55 | B58: GASTRONOMÍA ITALIANA EN COLOMBIA S.A.S | D58: ADM | E58: =IF(OR(B58="",C58=""),"",IFERROR(VLOOKUP(B58&"|||"&C58,MAESTRA!$A$3:$J$500,6,0),"⚠ No encontrado")) | F58: =IF(OR(B58="",C58=""),"",IFERROR(VLOOKUP(B58&"|||"&C58,MAESTRA!$A$3:$J$500,7,0),"⚠ No encontrado")) | G58: Reuniones gerenciales CEM (Comida) | H58: =IF(OR(B58="",C58=""),"",IFERROR(VLOOKUP(B58&"|||"&C58,MAESTRA!$A$3:$J$500,9,0),"")) | I58: NO PAGAR LEGALIZA RAFA, GINNA Y MARIANA TARJETAS PEOPLE ALMUERZO CEM | J58: Calle 100 | K58: NTFE145171 | L58: 46071 | N58: 362100 | O58: 5191 | P58: 46079 | Q58: QUEDA SALDO DE MARIANA POR VALOR DE $ 107,100 | R58: APROBACIÓN GERENCIA DE PERSONAS Y ADMÓN | T58: febrero 2026
A59: 56 | B59: CADENA COMERCIAL OXXO COLOMBIA S A S | D59: ADM | E59: =IF(OR(B59="",C59=""),"",IFERROR(VLOOKUP(B59&"|||"&C59,MAESTRA!$A$3:$J$500,6,0),"⚠ No encontrado")) | F59: =IF(OR(B59="",C59=""),"",IFERROR(VLOOKUP(B59&"|||"&C59,MAESTRA!$A$3:$J$500,7,0),"⚠ No encontrado")) | G59: Reuniones gerenciales CEM (Comida) | H59: =IF(OR(B59="",C59=""),"",IFERROR(VLOOKUP(B59&"|||"&C59,MAESTRA!$A$3:$J$500,9,0),"")) | I59: NO PAGAR LEGALIZA RAFAEL DE SA TARJETA PEOPLE PASS COMPRA QUESOS DESAYUNO CEM | J59: Calle 100 | K59: 334C257427 | L59: 46071 | N59: 35100 | O59: 5194 | P59: 46079 | R59: APROBACIÓN GERENCIA DE PERSONAS Y ADMÓN | T59: febrero 2026
A60: 57 | B60: GASEOSAS LUX S.A.S. | D60: ADM | E60: =IF(OR(B60="",C60=""),"",IFERROR(VLOOKUP(B60&"|||"&C60,MAESTRA!$A$3:$J$500,6,0),"⚠ No encontrado")) | F60: =IF(OR(B60="",C60=""),"",IFERROR(VLOOKUP(B60&"|||"&C60,MAESTRA!$A$3:$J$500,7,0),"⚠ No encontrado")) | G60: Material Copa/Cozinha | H60: =IF(OR(B60="",C60=""),"",IFERROR(VLOOKUP(B60&"|||"&C60,MAESTRA!$A$3:$J$500,9,0),"")) | I60: NO PAGAR LEGALIZA CAJA MENOR AEROPUERTO COMPRA 3 BOTELLONES DE AGUA | J60: Aeropuerto | K60: GL071338924 | L60: 46071 | N60: 40050 | R60: APROBACIÓN GERENCIA DE PERSONAS Y ADMÓN | T60: febrero 2026
A61: 58 | B61: CAMARA COMERCIO DE CALI | D61: ADM | E61: =IF(OR(B61="",C61=""),"",IFERROR(VLOOKUP(B61&"|||"&C61,MAESTRA!$A$3:$J$500,6,0),"⚠ No encontrado")) | F61: =IF(OR(B61="",C61=""),"",IFERROR(VLOOKUP(B61&"|||"&C61,MAESTRA!$A$3:$J$500,7,0),"⚠ No encontrado")) | G61: Trámites notariales autenticaciones | H61: =IF(OR(B61="",C61=""),"",IFERROR(VLOOKUP(B61&"|||"&C61,MAESTRA!$A$3:$J$500,9,0),"")) | I61: NO PAGAR LEGALIZA CAJA MENOR BOGOTA COMPRA CERTIFICADO CRA CIO LOGISTICA FACIL | J61: Cali | K61: 27VT267179 | L61: 46071 | N61: 12100 | O61: 5 | P61: 46079 | R61: APROBACIÓN GERENCIA DE PERSONAS Y ADMÓN | T61: febrero 2026
A62: 59 | B62: CADENA COMERCIAL OXXO COLOMBIA S A S | D62: ADM | E62: =IF(OR(B62="",C62=""),"",IFERROR(VLOOKUP(B62&"|||"&C62,MAESTRA!$A$3:$J$500,6,0),"⚠ No encontrado")) | F62: =IF(OR(B62="",C62=""),"",IFERROR(VLOOKUP(B62&"|||"&C62,MAESTRA!$A$3:$J$500,7,0),"⚠ No encontrado")) | G62: Reuniones gerenciales CEM (Comida) | H62: =IF(OR(B62="",C62=""),"",IFERROR(VLOOKUP(B62&"|||"&C62,MAESTRA!$A$3:$J$500,9,0),"")) | I62: NO PAGAR LEGALIZA TC 9994 COMPRA GASEOSA ALMUERZO CEM | J62: Transversal | K62: 334C257602 | L62: 46071 | N62: 21000 | O62: 5202 | P62: 46079 | R62: APROBACIÓN GERENCIA DE PERSONAS Y ADMÓN | T62: febrero 2026
A63: 60 | B63: CADENA COMERCIAL OXXO COLOMBIA S A S | D63: ADM | E63: =IF(OR(B63="",C63=""),"",IFERROR(VLOOKUP(B63&"|||"&C63,MAESTRA!$A$3:$J$500,6,0),"⚠ No encontrado")) | F63: =IF(OR(B63="",C63=""),"",IFERROR(VLOOKUP(B63&"|||"&C63,MAESTRA!$A$3:$J$500,7,0),"⚠ No encontrado")) | G63: Reuniones gerenciales CEM (Comida) | H63: =IF(OR(B63="",C63=""),"",IFERROR(VLOOKUP(B63&"|||"&C63,MAESTRA!$A$3:$J$500,9,0),"")) | I63: NO PAGAR LEGALIZA TARJETA PEOPLE PASS RAFAEL DE SA COMPARA AGUA REUNION CEM | J63: Transversal | K63: 334C257039 | L63: 46070 | N63: 55900 | O63: 5205 | P63: 46079 | R63: APROBACIÓN GERENCIA DE PERSONAS Y ADMÓN | T63: febrero 2026
A64: 61 | B64: CADENA COMERCIAL OXXO COLOMBIA S A S | D64: GH | E64: =IF(OR(B64="",C64=""),"",IFERROR(VLOOKUP(B64&"|||"&C64,MAESTRA!$A$3:$J$500,6,0),"⚠ No encontrado")) | F64: =IF(OR(B64="",C64=""),"",IFERROR(VLOOKUP(B64&"|||"&C64,MAESTRA!$A$3:$J$500,7,0),"⚠ No encontrado")) | G64: Plan estratégico en enero 2025 | H64: =IF(OR(B64="",C64=""),"",IFERROR(VLOOKUP(B64&"|||"&C64,MAESTRA!$A$3:$J$500,9,0),"")) | I64: NO PAGAR LEGALIZA TARJETA PEOPLE PASS GINNA CASTRO COMPRA DESAYUNO REUNION COMERCIAL | J64: Calle 100 | K64: 234C221718 | L64: 46069 | N64: 16800 | O64: 5210 | P64: 46079 | R64: APROBACIÓN GERENCIA DE PERSONAS Y ADMÓN | T64: febrero 2026
A65: 62 | B65: CADENA COMERCIAL OXXO COLOMBIA S A S | D65: GH | E65: =IF(OR(B65="",C65=""),"",IFERROR(VLOOKUP(B65&"|||"&C65,MAESTRA!$A$3:$J$500,6,0),"⚠ No encontrado")) | F65: =IF(OR(B65="",C65=""),"",IFERROR(VLOOKUP(B65&"|||"&C65,MAESTRA!$A$3:$J$500,7,0),"⚠ No encontrado")) | G65: Plan estratégico en enero 2025 | H65: =IF(OR(B65="",C65=""),"",IFERROR(VLOOKUP(B65&"|||"&C65,MAESTRA!$A$3:$J$500,9,0),"")) | I65: NO PAGAR LEGALIZA CAJA MENOR BOGOTA DESAYUNO COMERCIAL | J65: Calle 100 | K65: 334C259243 | L65: 46076 | N65: 35500 | O65: 5214 | P65: 46079 | R65: APROBACIÓN GERENCIA DE PERSONAS Y ADMÓN | T65: febrero 2026
A66: 63 | B66: GLOBAL OPERADORA HOTELERA SAS | D66: ADM | E66: =IF(OR(B66="",C66=""),"",IFERROR(VLOOKUP(B66&"|||"&C66,MAESTRA!$A$3:$J$500,6,0),"⚠ No encontrado")) | F66: =IF(OR(B66="",C66=""),"",IFERROR(VLOOKUP(B66&"|||"&C66,MAESTRA!$A$3:$J$500,7,0),"⚠ No encontrado")) | G66: Gastos De Representacion | H66: =IF(OR(B66="",C66=""),"",IFERROR(VLOOKUP(B66&"|||"&C66,MAESTRA!$A$3:$J$500,9,0),"")) | I66: NO PAGAR LAGALIZA WILLIAM MARTIMNEZ ALMUERZO CLIENTE ZIX | J66: Calle 100 | K66: 7RE47087 | L66: 46065 | N66: 415252 | O66: 5217 | P66: 46079 | T66: febrero 2026
A67: 64 | B67: CAMARA DE COMERCIO DE BOGOTA | D67: ADM | E67: =IF(OR(B67="",C67=""),"",IFERROR(VLOOKUP(B67&"|||"&C67,MAESTRA!$A$3:$J$500,6,0),"⚠ No encontrado")) | F67: =IF(OR(B67="",C67=""),"",IFERROR(VLOOKUP(B67&"|||"&C67,MAESTRA!$A$3:$J$500,7,0),"⚠ No encontrado")) | G67: Trámites notariales autenticaciones | H67: =IF(OR(B67="",C67=""),"",IFERROR(VLOOKUP(B67&"|||"&C67,MAESTRA!$A$3:$J$500,9,0),"")) | I67: NO PAGAR LEGALIZA CAJA MENOR BOGOTA COMPRA CERTIFICADO CAMRA COMERCIO CRAFT | J67: Calle 100 | K67: TV4310011749 | L67: 46085 | N67: 12100 | O67: 470 | P67: 46086 | T67: marzo 2026
A68: 65 | B68: CASALIMPIA SA | D68: ADM | E68: =IF(OR(B68="",C68=""),"",IFERROR(VLOOKUP(B68&"|||"&C68,MAESTRA!$A$3:$J$500,6,0),"⚠ No encontrado")) | F68: =IF(OR(B68="",C68=""),"",IFERROR(VLOOKUP(B68&"|||"&C68,MAESTRA!$A$3:$J$500,7,0),"⚠ No encontrado")) | G68: Otros Gastos CASA LIMPIA PLANILLA AC OTROS | H68: =IF(OR(B68="",C68=""),"",IFERROR(VLOOKUP(B68&"|||"&C68,MAESTRA!$A$3:$J$500,9,0),"")) | I68: NO PAGAR LEGALIZA TC 9994 ASEO OFICINA CRAFT BARRANQUILLA MESES MARZO Y ABRIL | J68: Barranquilla | K68: AP227714 | L68: 46080 | N68: 983520 | O68: 8 | P68: 46086 | T68: febrero 2026
A69: 66 | B69: COLOMBIANA DE COMERCIO S.A. | D69: ADM | E69: =IF(OR(B69="",C69=""),"",IFERROR(VLOOKUP(B69&"|||"&C69,MAESTRA!$A$3:$J$500,6,0),"⚠ No encontrado")) | F69: =IF(OR(B69="",C69=""),"",IFERROR(VLOOKUP(B69&"|||"&C69,MAESTRA!$A$3:$J$500,7,0),"⚠ No encontrado")) | G69: Mejoramiento espacios de trabajo | H69: =IF(OR(B69="",C69=""),"",IFERROR(VLOOKUP(B69&"|||"&C69,MAESTRA!$A$3:$J$500,9,0),"")) | I69: NO PAGAR LEGALIZA TC 9994 COMPRA HORNO MICROHONDAS | J69: Calle 100 | K69: X3812535445 | L69: 46079 | N69: 377800 | O69: 6284 | P69: 46086 | T69: febrero 2026
A70: 67 | B70: CADENA COMERCIAL OXXO COLOMBIA S A S | D70: GH | E70: =IF(OR(B70="",C70=""),"",IFERROR(VLOOKUP(B70&"|||"&C70,MAESTRA!$A$3:$J$500,6,0),"⚠ No encontrado")) | F70: =IF(OR(B70="",C70=""),"",IFERROR(VLOOKUP(B70&"|||"&C70,MAESTRA!$A$3:$J$500,7,0),"⚠ No encontrado")) | G70: Plan estratégico en enero 2025 | H70: =IF(OR(B70="",C70=""),"",IFERROR(VLOOKUP(B70&"|||"&C70,MAESTRA!$A$3:$J$500,9,0),"")) | I70: NO PAGAR LEGALIZA CAJA MENOR BOGOTA DESAYUNO REUNION FINANCIERO | J70: Calle 100 | K70: 334C260430 | L70: 46078 | N70: 99050 | O70: 6281 | P70: 46086 | R70: APROBACIÓN GERENCIA DE PERSONAS Y ADMÓN | T70: febrero 2026
A71: 68 | B71: MAQUITE S.A. | D71: ADM | E71: =IF(OR(B71="",C71=""),"",IFERROR(VLOOKUP(B71&"|||"&C71,MAESTRA!$A$3:$J$500,6,0),"⚠ No encontrado")) | F71: =IF(OR(B71="",C71=""),"",IFERROR(VLOOKUP(B71&"|||"&C71,MAESTRA!$A$3:$J$500,7,0),"⚠ No encontrado")) | G71: Gastos De Representacion | H71: =IF(OR(B71="",C71=""),"",IFERROR(VLOOKUP(B71&"|||"&C71,MAESTRA!$A$3:$J$500,9,0),"")) | I71: NO PAGAR LEGALIZA CAJA MENOR CALI ALMUERZO CLIENTE ASEINTEGRAL DIANA GRACIA | J71: Cali | K71: R04R583087 | L71: 46062 | N71: 101700 | O71: 6 | P71: 46086 | T71: febrero 2026
A72: 69 | B72: LISDEY MARYORY CARDONA OSPINA | D72: ADM | E72: =IF(OR(B72="",C72=""),"",IFERROR(VLOOKUP(B72&"|||"&C72,MAESTRA!$A$3:$J$500,6,0),"⚠ No encontrado")) | F72: =IF(OR(B72="",C72=""),"",IFERROR(VLOOKUP(B72&"|||"&C72,MAESTRA!$A$3:$J$500,7,0),"⚠ No encontrado")) | G72: Material Copa/Cozinha | H72: =IF(OR(B72="",C72=""),"",IFERROR(VLOOKUP(B72&"|||"&C72,MAESTRA!$A$3:$J$500,9,0),"")) | I72: NO PAGAR LEGALIZA CAJA MENOR CARTAGENA COMPRA BOTELLON DE AGUA | J72: Cartagena | K72: FELM33486 | L72: 46080 | N72: 18000 | O72: 30 | P72: 46086 | T72: febrero 2026
A73: 70 | B73: SUPERMARKET LA COLOMBIANA SAS ZOMAC | D73: ADM | E73: =IF(OR(B73="",C73=""),"",IFERROR(VLOOKUP(B73&"|||"&C73,MAESTRA!$A$3:$J$500,6,0),"⚠ No encontrado")) | F73: =IF(OR(B73="",C73=""),"",IFERROR(VLOOKUP(B73&"|||"&C73,MAESTRA!$A$3:$J$500,7,0),"⚠ No encontrado")) | G73: Material Copa/Cozinha | H73: =IF(OR(B73="",C73=""),"",IFERROR(VLOOKUP(B73&"|||"&C73,MAESTRA!$A$3:$J$500,9,0),"")) | I73: NO PAGAR LEGALIZA CAJA MENOR BUENAVENTURA COMPRA BOTELLON DE AGUA | J73: Buenaventura | K73: SMEF50152 | L73: 46080 | N73: 30000 | O73: 28 | P73: 46086 | T73: febrero 2026
A74: 71 | B74: CREPES Y WAFFLES S A | D74: GH | E74: =IF(OR(B74="",C74=""),"",IFERROR(VLOOKUP(B74&"|||"&C74,MAESTRA!$A$3:$J$500,6,0),"⚠ No encontrado")) | F74: =IF(OR(B74="",C74=""),"",IFERROR(VLOOKUP(B74&"|||"&C74,MAESTRA!$A$3:$J$500,7,0),"⚠ No encontrado")) | G74: Cumpleaños | H74: =IF(OR(B74="",C74=""),"",IFERROR(VLOOKUP(B74&"|||"&C74,MAESTRA!$A$3:$J$500,9,0),"")) | I74: NO PAGAR LEGALIZA CAJA MENOR BOGOTA COMPRA HELADO TATIANA Y ELEONORA DE CUMPLE | J74: Transversal | K74: R06E478485 | L74: 46084 | N74: 29800 | O74: 481 | P74: 46086 | T74: marzo 2026
A75: 72 | B75: CENTURY SPORTS S A S | D75: GH | E75: =IF(OR(B75="",C75=""),"",IFERROR(VLOOKUP(B75&"|||"&C75,MAESTRA!$A$3:$J$500,6,0),"⚠ No encontrado")) | F75: =IF(OR(B75="",C75=""),"",IFERROR(VLOOKUP(B75&"|||"&C75,MAESTRA!$A$3:$J$500,7,0),"⚠ No encontrado")) | G75: Cumpleaños | H75: =IF(OR(B75="",C75=""),"",IFERROR(VLOOKUP(B75&"|||"&C75,MAESTRA!$A$3:$J$500,9,0),"")) | I75: NO PAGAR LEGALIZA MARIANA MUNAR BONO DE CUMPLEAÑOS TATIANA SANCHEZ | J75: Calle 100 | K75: S6026127 | L75: 46079 | N75: 100000 | O75: 6285 | P75: 46086 | T75: febrero 2026
A76: 73 | B76: TAGLIATA S.A.S | D76: ADM | E76: =IF(OR(B76="",C76=""),"",IFERROR(VLOOKUP(B76&"|||"&C76,MAESTRA!$A$3:$J$500,6,0),"⚠ No encontrado")) | F76: =IF(OR(B76="",C76=""),"",IFERROR(VLOOKUP(B76&"|||"&C76,MAESTRA!$A$3:$J$500,7,0),"⚠ No encontrado")) | G76: Gastos De Representacion | H76: =IF(OR(B76="",C76=""),"",IFERROR(VLOOKUP(B76&"|||"&C76,MAESTRA!$A$3:$J$500,9,0),"")) | I76: NO PGAR LEGALIZA STEFANNY HERNANDEZ ALMUERZO CLIENTE LOGIMPEX | J76: Medellín | K76: FE20026 | L76: 46071 | N76: 242993 | O76: 72 | P76: 46086 | T76: febrero 2026
A77: 74 | B77: ERIKA TATIANA VARGAS GALLARDO | D77: GH | E77: =IF(OR(B77="",C77=""),"",IFERROR(VLOOKUP(B77&"|||"&C77,MAESTRA!$A$3:$J$500,6,0),"⚠ No encontrado")) | F77: =IF(OR(B77="",C77=""),"",IFERROR(VLOOKUP(B77&"|||"&C77,MAESTRA!$A$3:$J$500,7,0),"⚠ No encontrado")) | G77: Detalles en momentos especificos (Matrimonio, grados, fallecimientos) | H77: =IF(OR(B77="",C77=""),"",IFERROR(VLOOKUP(B77&"|||"&C77,MAESTRA!$A$3:$J$500,9,0),"")) | I77: NO PAGAR LEGALIZA MARIANA MUNAR VELA DE CONDOLENCIAS ANA FERNANDEZ POR PÉRDIDA DE MASCOTA | J77: Calle 100 | K77: FEV68 | L77: 46062 | N77: 87500 | O77: 6286 | P77: 46086 | T77: febrero 2026
A78: 75 | B78: CREPES Y WAFFLES S A | D78: GH | E78: =IF(OR(B78="",C78=""),"",IFERROR(VLOOKUP(B78&"|||"&C78,MAESTRA!$A$3:$J$500,6,0),"⚠ No encontrado")) | F78: =IF(OR(B78="",C78=""),"",IFERROR(VLOOKUP(B78&"|||"&C78,MAESTRA!$A$3:$J$500,7,0),"⚠ No encontrado")) | G78: Café / Almuerzo con colaboradores | H78: =IF(OR(B78="",C78=""),"",IFERROR(VLOOKUP(B78&"|||"&C78,MAESTRA!$A$3:$J$500,9,0),"")) | I78: NO PAGAR LEGALIZA TC BB 0206 ALMUERZO DE TRABAJO AACR Y SILVIA TRIANA | J78: Calle 100 | K78: R06E469303 | L78: 46064 | N78: 137800 | O78: 6805 | P78: 46089 | T78: febrero 2026
A79: 76 | B79: CREPES Y WAFFLES S A | D79: GH | E79: =IF(OR(B79="",C79=""),"",IFERROR(VLOOKUP(B79&"|||"&C79,MAESTRA!$A$3:$J$500,6,0),"⚠ No encontrado")) | F79: =IF(OR(B79="",C79=""),"",IFERROR(VLOOKUP(B79&"|||"&C79,MAESTRA!$A$3:$J$500,7,0),"⚠ No encontrado")) | G79: Café / Almuerzo con colaboradores | H79: =IF(OR(B79="",C79=""),"",IFERROR(VLOOKUP(B79&"|||"&C79,MAESTRA!$A$3:$J$500,9,0),"")) | I79: NO PAGAR LEGALIZA TC NUEVA DE AACR DESAYUNO DE TRABAJO CON ANGEE GOMEZ | J79: Calle 100 | K79: R06E475448 | L79: 46078 | N79: 210200 | O79: 6807 | P79: 46089 | T79: febrero 2026
A80: 77 | B80: DOMIORIENTE SAS | D80: GH | E80: =IF(OR(B80="",C80=""),"",IFERROR(VLOOKUP(B80&"|||"&C80,MAESTRA!$A$3:$J$500,6,0),"⚠ No encontrado")) | F80: =IF(OR(B80="",C80=""),"",IFERROR(VLOOKUP(B80&"|||"&C80,MAESTRA!$A$3:$J$500,7,0),"⚠ No encontrado")) | G80: Actividades Semana de la Salud | H80: =IF(OR(B80="",C80=""),"",IFERROR(VLOOKUP(B80&"|||"&C80,MAESTRA!$A$3:$J$500,9,0),"")) | I80: NO PAGAR LEGALIZA CAJA MENOR BOGOTA REFRIGERIO EN BARRNQUILLA SEMANA DE LA SALUD | J80: Barranquilla | K80: SON102105 | L80: 46086 | N80: 64800 | O80: 5 | P80: 46093 | T80: marzo 2026
A81: 78 | B81: CASALIMPIA SA | D81: ADM | E81: =IF(OR(B81="",C81=""),"",IFERROR(VLOOKUP(B81&"|||"&C81,MAESTRA!$A$3:$J$500,6,0),"⚠ No encontrado")) | F81: =IF(OR(B81="",C81=""),"",IFERROR(VLOOKUP(B81&"|||"&C81,MAESTRA!$A$3:$J$500,7,0),"⚠ No encontrado")) | G81: Otros Gastos CASA LIMPIA PLANILLA AC OTROS | H81: =IF(OR(B81="",C81=""),"",IFERROR(VLOOKUP(B81&"|||"&C81,MAESTRA!$A$3:$J$500,9,0),"")) | I81: NO PAGAR LEGALIZA ELEONORA FLOREZ ASEO OF CRAFT CALI | J81: Cali | K81: AP228386 | L81: 46090 | N81: 546400 | O81: 5 | P81: 46093 | T81: marzo 2026
A82: 79 | B82: GASTRONOMÍA ITALIANA EN COLOMBIA S.A.S | D82: ADM | E82: =IF(OR(B82="",C82=""),"",IFERROR(VLOOKUP(B82&"|||"&C82,MAESTRA!$A$3:$J$500,6,0),"⚠ No encontrado")) | F82: =IF(OR(B82="",C82=""),"",IFERROR(VLOOKUP(B82&"|||"&C82,MAESTRA!$A$3:$J$500,7,0),"⚠ No encontrado")) | G82: Café / Almuerzo con colaboradores | H82: =IF(OR(B82="",C82=""),"",IFERROR(VLOOKUP(B82&"|||"&C82,MAESTRA!$A$3:$J$500,9,0),"")) | I82: NO PGAR LEGALIZA TC O2026 COMPRA PIZZAN ATENCION COLBORDORES DONACION CORDOBA | J82: Calle 100 | K82: HIFE269740 | L82: 46091 | N82: 129700 | O82: 1905 | P82: 46093 | T82: marzo 2026
A83: 80 | B83: CADENA COMERCIAL OXXO COLOMBIA S A S | D83: GH | E83: =IF(OR(B83="",C83=""),"",IFERROR(VLOOKUP(B83&"|||"&C83,MAESTRA!$A$3:$J$500,6,0),"⚠ No encontrado")) | F83: =IF(OR(B83="",C83=""),"",IFERROR(VLOOKUP(B83&"|||"&C83,MAESTRA!$A$3:$J$500,7,0),"⚠ No encontrado")) | G83: Café / Almuerzo con colaboradores | H83: =IF(OR(B83="",C83=""),"",IFERROR(VLOOKUP(B83&"|||"&C83,MAESTRA!$A$3:$J$500,9,0),"")) | I83: NO PAGAR LEGALIZA TC 0206 COMPRA GASEOSA ATENCION COLAB DONACION CORDOBA | J83: Calle 100 | K83: 334C266980 | L83: 46091 | N83: 12300 | O83: 1906 | P83: 46093 | R83: APROBACIÓN GERENCIA DE PERSONAS Y ADMÓN | T83: marzo 2026
A84: 81 | B84: SUPERMARKET LA COLOMBIANA SAS ZOMAC | D84: ADM | E84: =IF(OR(B84="",C84=""),"",IFERROR(VLOOKUP(B84&"|||"&C84,MAESTRA!$A$3:$J$500,6,0),"⚠ No encontrado")) | F84: =IF(OR(B84="",C84=""),"",IFERROR(VLOOKUP(B84&"|||"&C84,MAESTRA!$A$3:$J$500,7,0),"⚠ No encontrado")) | G84: Material Copa/Cozinha | H84: =IF(OR(B84="",C84=""),"",IFERROR(VLOOKUP(B84&"|||"&C84,MAESTRA!$A$3:$J$500,9,0),"")) | I84: NO PAGAR LEGALIZA CAJA MENOR BUENAVENTURA COMPRA BOTELLON AGUA | J84: Buenaventura | K84: SMEF51883 | L84: 46091 | N84: 30000 | O84: 9 | P84: 46093 | T84: marzo 2026
A85: 82 | B85: LA BIFERIA SA | D85: ADM | E85: =IF(OR(B85="",C85=""),"",IFERROR(VLOOKUP(B85&"|||"&C85,MAESTRA!$A$3:$J$500,6,0),"⚠ No encontrado")) | F85: =IF(OR(B85="",C85=""),"",IFERROR(VLOOKUP(B85&"|||"&C85,MAESTRA!$A$3:$J$500,7,0),"⚠ No encontrado")) | G85: Gastos De Representacion | H85: =IF(OR(B85="",C85=""),"",IFERROR(VLOOKUP(B85&"|||"&C85,MAESTRA!$A$3:$J$500,9,0),"")) | I85: NO PAGAR LEGALIZA EDUARD HERNANDEZ ALMUERZO CLIENTE SEA AIR GLOBAL SOLUTIONS | J85: Calle 100 | K85: FEB574158 | L85: 46087 | N85: 203878 | O85: 1908 | P85: 46093 | T85: marzo 2026
A86: 83 | B86: CASALIMPIA SA | D86: ADM | E86: =IF(OR(B86="",C86=""),"",IFERROR(VLOOKUP(B86&"|||"&C86,MAESTRA!$A$3:$J$500,6,0),"⚠ No encontrado")) | F86: =IF(OR(B86="",C86=""),"",IFERROR(VLOOKUP(B86&"|||"&C86,MAESTRA!$A$3:$J$500,7,0),"⚠ No encontrado")) | G86: Otros Gastos CASA LIMPIA PLANILLA AC OTROS | H86: =IF(OR(B86="",C86=""),"",IFERROR(VLOOKUP(B86&"|||"&C86,MAESTRA!$A$3:$J$500,9,0),"")) | I86: NO PAGAR LEGALIZA ELEONORA FLOREZ COMPRA UN SERVICIO DE CASALIMPIA AEROPUERTO | J86: Aeropuerto | K86: AP229001 | L86: 46093 | N86: 143700 | O86: 3 | P86: 46099 | T86: marzo 2026
A87: 84 | B87: CADENA COMERCIAL OXXO COLOMBIA S A S | D87: ADM | E87: =IF(OR(B87="",C87=""),"",IFERROR(VLOOKUP(B87&"|||"&C87,MAESTRA!$A$3:$J$500,6,0),"⚠ No encontrado")) | F87: =IF(OR(B87="",C87=""),"",IFERROR(VLOOKUP(B87&"|||"&C87,MAESTRA!$A$3:$J$500,7,0),"⚠ No encontrado")) | G87: Regalos clientes | H87: =IF(OR(B87="",C87=""),"",IFERROR(VLOOKUP(B87&"|||"&C87,MAESTRA!$A$3:$J$500,9,0),"")) | I87: NO PAGAR LEGALIZA CAJA MENOR BOGOTA CHOCOLATINAS ATENCON CLIENTE LOVILIZAR CARGA | J87: Calle 100 | K87: 334C267591 | L87: 46092 | N87: 24100 | O87: 3209 | P87: 46099 | R87: APROBACIÓN GERENCIA DE PERSONAS Y ADMÓN | T87: marzo 2026
A88: 85 | B88: CREPES Y WAFFLES S A | D88: GH | E88: =IF(OR(B88="",C88=""),"",IFERROR(VLOOKUP(B88&"|||"&C88,MAESTRA!$A$3:$J$500,6,0),"⚠ No encontrado")) | F88: =IF(OR(B88="",C88=""),"",IFERROR(VLOOKUP(B88&"|||"&C88,MAESTRA!$A$3:$J$500,7,0),"⚠ No encontrado")) | G88: Dia de la mujer | H88: =IF(OR(B88="",C88=""),"",IFERROR(VLOOKUP(B88&"|||"&C88,MAESTRA!$A$3:$J$500,9,0),"")) | I88: NO PAGAR LEGALIZA MARIANA MUNAR APORTE DÍA DE LA MUJER | J88: Transversal | K88: R06E479666 | L88: 46087 | N88: 959000 | O88: 3215 | P88: 46099 | T88: marzo 2026
A89: 86 | B89: CADENA COMERCIAL OXXO COLOMBIA S A S | D89: GH | E89: =IF(OR(B89="",C89=""),"",IFERROR(VLOOKUP(B89&"|||"&C89,MAESTRA!$A$3:$J$500,6,0),"⚠ No encontrado")) | F89: =IF(OR(B89="",C89=""),"",IFERROR(VLOOKUP(B89&"|||"&C89,MAESTRA!$A$3:$J$500,7,0),"⚠ No encontrado")) | G89: Actividades Semana de la Salud | H89: =IF(OR(B89="",C89=""),"",IFERROR(VLOOKUP(B89&"|||"&C89,MAESTRA!$A$3:$J$500,9,0),"")) | I89: NO PAGAR LEGALIZA CAJA MENOR BOG COMPRA GAESOSA SEMANA DE LA SALID CRAFT AEROPUERTO | J89: Aeropuerto | K89: 2SVV173649 | L89: 46086 | N89: 23750 | O89: 4 | P89: 46099 | R89: APROBACIÓN GERENCIA DE PERSONAS Y ADMÓN | T89: marzo 2026
A90: 87 | B90: CRISTALERIA LA REINA S.A.S | D90: ADM | E90: =IF(OR(B90="",C90=""),"",IFERROR(VLOOKUP(B90&"|||"&C90,MAESTRA!$A$3:$J$500,6,0),"⚠ No encontrado")) | F90: =IF(OR(B90="",C90=""),"",IFERROR(VLOOKUP(B90&"|||"&C90,MAESTRA!$A$3:$J$500,7,0),"⚠ No encontrado")) | G90: Conservacion Y Manutenimiento De Oficina | H90: =IF(OR(B90="",C90=""),"",IFERROR(VLOOKUP(B90&"|||"&C90,MAESTRA!$A$3:$J$500,9,0),"")) | I90: NO PAGAR LEGALIZA CAJA MENOR BUN COMPRA SILLAS RIMAX PARA USO COMEDOR | J90: Buenaventura | K90: FER113454 | L90: 46098 | N90: 100000 | O90: 13 | P90: 46100 | T90: marzo 2026
A91: 88 | B91: CASALIMPIA SA | D91: ADM | E91: =IF(OR(B91="",C91=""),"",IFERROR(VLOOKUP(B91&"|||"&C91,MAESTRA!$A$3:$J$500,6,0),"⚠ No encontrado")) | F91: =IF(OR(B91="",C91=""),"",IFERROR(VLOOKUP(B91&"|||"&C91,MAESTRA!$A$3:$J$500,7,0),"⚠ No encontrado")) | G91: Otros Gastos CASA LIMPIA PLANILLA AC OTROS | H91: =IF(OR(B91="",C91=""),"",IFERROR(VLOOKUP(B91&"|||"&C91,MAESTRA!$A$3:$J$500,9,0),"")) | I91: NO PAGAR LEFALIZA TC 9994 COMPRA SERVICIO ASEO CRAFT AEROPUERTO HASTA ABRIL | J91: Aeropuerto | K91: AP229445 | L91: 46098 | N91: 1422629 | O91: 7 | P91: 46100 | T91: marzo 2026
A92: 89 | B92: OSCAR ANTONIO HERNANDEZ GOMEZ | D92: ADM | E92: =IF(OR(B92="",C92=""),"",IFERROR(VLOOKUP(B92&"|||"&C92,MAESTRA!$A$3:$J$500,6,0),"⚠ No encontrado")) | F92: =IF(OR(B92="",C92=""),"",IFERROR(VLOOKUP(B92&"|||"&C92,MAESTRA!$A$3:$J$500,7,0),"⚠ No encontrado")) | G92: Trámites notariales autenticaciones | H92: =IF(OR(B92="",C92=""),"",IFERROR(VLOOKUP(B92&"|||"&C92,MAESTRA!$A$3:$J$500,9,0),"")) | I92: NO PAGAR LEGALIZA CAJA MENOR BOGOTA AUTENTICA CARTA MSC SAMANTHA | J92: Calle 100 | K92: FEV145031 | L92: 46098 | N92: 3998 | O92: 3445 | P92: 46100 | T92: marzo 2026
A93: 90 | B93: SUPERMARKET LA COLOMBIANA SAS ZOMAC | D93: ADM | E93: =IF(OR(B93="",C93=""),"",IFERROR(VLOOKUP(B93&"|||"&C93,MAESTRA!$A$3:$J$500,6,0),"⚠ No encontrado")) | F93: =IF(OR(B93="",C93=""),"",IFERROR(VLOOKUP(B93&"|||"&C93,MAESTRA!$A$3:$J$500,7,0),"⚠ No encontrado")) | G93: Material Copa/Cozinha | H93: =IF(OR(B93="",C93=""),"",IFERROR(VLOOKUP(B93&"|||"&C93,MAESTRA!$A$3:$J$500,9,0),"")) | I93: NO PAGAR LEGALZA CAJA MENOR BUENAVENTURA COMPRA BOTELLON AGUA | J93: Buenaventura | K93: SMEF53066 | L93: 46098 | N93: 30000 | O93: 14 | P93: 46100 | T93: marzo 2026
A94: 91 | B94: CREPES Y WAFFLES S A | D94: GH | E94: =IF(OR(B94="",C94=""),"",IFERROR(VLOOKUP(B94&"|||"&C94,MAESTRA!$A$3:$J$500,6,0),"⚠ No encontrado")) | F94: =IF(OR(B94="",C94=""),"",IFERROR(VLOOKUP(B94&"|||"&C94,MAESTRA!$A$3:$J$500,7,0),"⚠ No encontrado")) | G94: Dia de la mujer | H94: =IF(OR(B94="",C94=""),"",IFERROR(VLOOKUP(B94&"|||"&C94,MAESTRA!$A$3:$J$500,9,0),"")) | I94: NO PAGAR LEGALIZA MARIANA MUNAR APORTE DÍA DE LA MUJER | J94: Transversal | K94: R06E479666 | L94: 46087 | N94: 959000 | O94: 3215 | P94: 46100 | T94: marzo 2026
A95: 92 | B95: CADENA COMERCIAL OXXO COLOMBIA S A S | D95: GH | E95: =IF(OR(B95="",C95=""),"",IFERROR(VLOOKUP(B95&"|||"&C95,MAESTRA!$A$3:$J$500,6,0),"⚠ No encontrado")) | F95: =IF(OR(B95="",C95=""),"",IFERROR(VLOOKUP(B95&"|||"&C95,MAESTRA!$A$3:$J$500,7,0),"⚠ No encontrado")) | G95: Plan estratégico en enero 2025 | H95: =IF(OR(B95="",C95=""),"",IFERROR(VLOOKUP(B95&"|||"&C95,MAESTRA!$A$3:$J$500,9,0),"")) | I95: NO PAGAR LEGALIZA CAJA MENOR BOGOTA COMPRA DESAYUNO COMERCIAL | J95: Calle 100 | K95: 334C269936 | L95: 46097 | N95: 32200 | O95: 4905 | P95: 46107 | R95: APROBACIÓN GERENCIA DE PERSONAS Y ADMÓN | T95: marzo 2026
A96: 93 | B96: CAMARA DE COMERCIO DE BOGOTA | D96: ADM | E96: =IF(OR(B96="",C96=""),"",IFERROR(VLOOKUP(B96&"|||"&C96,MAESTRA!$A$3:$J$500,6,0),"⚠ No encontrado")) | F96: =IF(OR(B96="",C96=""),"",IFERROR(VLOOKUP(B96&"|||"&C96,MAESTRA!$A$3:$J$500,7,0),"⚠ No encontrado")) | G96: Trámites notariales autenticaciones | H96: =IF(OR(B96="",C96=""),"",IFERROR(VLOOKUP(B96&"|||"&C96,MAESTRA!$A$3:$J$500,9,0),"")) | I96: NO PAGAR LEGALIZA CAJA MENOR BOGOTA COMPRA CERTIFICADO CAMRA COMERCIO CRAFT | J96: Calle 100 | K96: TV4310145142 | L96: 46101 | N96: 12100 | O96: 4908 | P96: 46107 | T96: marzo 2026
A97: 94 | B97: BACO FOODS COLOMBIA S.A.S | D97: ADM | E97: =IF(OR(B97="",C97=""),"",IFERROR(VLOOKUP(B97&"|||"&C97,MAESTRA!$A$3:$J$500,6,0),"⚠ No encontrado")) | F97: =IF(OR(B97="",C97=""),"",IFERROR(VLOOKUP(B97&"|||"&C97,MAESTRA!$A$3:$J$500,7,0),"⚠ No encontrado")) | G97: Gastos De Representacion | H97: =IF(OR(B97="",C97=""),"",IFERROR(VLOOKUP(B97&"|||"&C97,MAESTRA!$A$3:$J$500,9,0),"")) | I97: NO PAGAR LEGALIZA NADIA MARTINEZ ALMUERZO CLIENTE | J97: Barranquilla | K97: E901169674 | L97: 46093 | N97: 186833 | O97: 4826 | P97: 46107 | T97: marzo 2026
A98: 95 | B98: ADIDAS | D98: GH | E98: =IF(OR(B98="",C98=""),"",IFERROR(VLOOKUP(B98&"|||"&C98,MAESTRA!$A$3:$J$500,6,0),"⚠ No encontrado")) | F98: =IF(OR(B98="",C98=""),"",IFERROR(VLOOKUP(B98&"|||"&C98,MAESTRA!$A$3:$J$500,7,0),"⚠ No encontrado")) | G98: Cumpleaños | H98: =IF(OR(B98="",C98=""),"",IFERROR(VLOOKUP(B98&"|||"&C98,MAESTRA!$A$3:$J$500,9,0),"")) | I98: NO PAGAR LEGALIZA MARIANA MUNAR BONO CUMPLEANOS JHON ESPINOSA MARZO 2026 | J98: Transversal | K98: 022A50871 | L98: 46103 | N98: 100000 | O98: 4911 | P98: 46107 | T98: marzo 2026
A99: 96 | B99: PRODUCTOS PARA EL ALMA SAS | D99: ADM | E99: =IF(OR(B99="",C99=""),"",IFERROR(VLOOKUP(B99&"|||"&C99,MAESTRA!$A$3:$J$500,6,0),"⚠ No encontrado")) | F99: =IF(OR(B99="",C99=""),"",IFERROR(VLOOKUP(B99&"|||"&C99,MAESTRA!$A$3:$J$500,7,0),"⚠ No encontrado")) | G99: Plan estratégico en enero 2025 | H99: =IF(OR(B99="",C99=""),"",IFERROR(VLOOKUP(B99&"|||"&C99,MAESTRA!$A$3:$J$500,9,0),"")) | I99: NO PAGAR LEGALIZA TARJETA PEOPLE PASS GINNA CASTRO COMPRA DESAYUNO REUNION COMERCIAL CEM | J99: Calle 100 | K99: FEJC26629 | L99: 46105 | N99: 67000 | O99: 7059 | P99: 46120 | T99: marzo 2026
A100: 97 | B100: ALMACENES ÉXITO S.A | D100: ADM | E100: =IF(OR(B100="",C100=""),"",IFERROR(VLOOKUP(B100&"|||"&C100,MAESTRA!$A$3:$J$500,6,0),"⚠ No encontrado")) | F100: =IF(OR(B100="",C100=""),"",IFERROR(VLOOKUP(B100&"|||"&C100,MAESTRA!$A$3:$J$500,7,0),"⚠ No encontrado")) | G100: Material Copa/Cozinha | H100: =IF(OR(B100="",C100=""),"",IFERROR(VLOOKUP(B100&"|||"&C100,MAESTRA!$A$3:$J$500,9,0),"")) | I100: NO PAGAR LEGALIZA TARJETA PEOPLE PASS GINNA CASTRO COMPRA DE 2 CAJAS DE AROMATICAS PARA ADRIANA CARDENAS | J100: Calle 100 | K100: UP0514054 | L100: 46104 | N100: 29700 | O100: 7062 | P100: 46120 | T100: marzo 2026
A101: 98 | B101: HARRYSA S.A.S | D101: ADM | E101: =IF(OR(B101="",C101=""),"",IFERROR(VLOOKUP(B101&"|||"&C101,MAESTRA!$A$3:$J$500,6,0),"⚠ No encontrado")) | F101: =IF(OR(B101="",C101=""),"",IFERROR(VLOOKUP(B101&"|||"&C101,MAESTRA!$A$3:$J$500,7,0),"⚠ No encontrado")) | G101: Gastos De Representacion | H101: =IF(OR(B101="",C101=""),"",IFERROR(VLOOKUP(B101&"|||"&C101,MAESTRA!$A$3:$J$500,9,0),"")) | I101: NO PAGAR LEGALIZA TC ACR CENA CLIENTE JAS CON WILLIAM MARTINEZ | J101: Calle 100 | K101: FEV160497 | L101: 46092 | N101: 1516518.6 | O101: 7057 | P101: 46120 | T101: marzo 2026
A102: 99 | B102: INVERSIONES SOMONTANO SAS | D102: ADM | E102: =IF(OR(B102="",C102=""),"",IFERROR(VLOOKUP(B102&"|||"&C102,MAESTRA!$A$3:$J$500,6,0),"⚠ No encontrado")) | F102: =IF(OR(B102="",C102=""),"",IFERROR(VLOOKUP(B102&"|||"&C102,MAESTRA!$A$3:$J$500,7,0),"⚠ No encontrado")) | G102: Gastos De Representacion | H102: =IF(OR(B102="",C102=""),"",IFERROR(VLOOKUP(B102&"|||"&C102,MAESTRA!$A$3:$J$500,9,0),"")) | I102: NO PAGAR LEGALIZA TC AACR ALMUERZO PROVEEDOR HAPAG LLOYD CON WILLIAM | J102: Calle 100 | K102: RPS81915 | L102: 46092 | N102: 565963 | O102: 7058 | P102: 46120 | T102: marzo 2026
A103: 100 | B103: LISDEY MARYORY CARDONA OSPINA | D103: ADM | E103: =IF(OR(B103="",C103=""),"",IFERROR(VLOOKUP(B103&"|||"&C103,MAESTRA!$A$3:$J$500,6,0),"⚠ No encontrado")) | F103: =IF(OR(B103="",C103=""),"",IFERROR(VLOOKUP(B103&"|||"&C103,MAESTRA!$A$3:$J$500,7,0),"⚠ No encontrado")) | G103: Material Copa/Cozinha | H103: =IF(OR(B103="",C103=""),"",IFERROR(VLOOKUP(B103&"|||"&C103,MAESTRA!$A$3:$J$500,9,0),"")) | I103: NO PAGAR LEGALIZA CAJA MENOR DE CARTAGENA COMPRA BOTELLON DE AGUA | J103: Cartagena | K103: FELM34805 | L103: 46108 | N103: 18000 | O103: 26 | P103: 46120 | T103: marzo 2026
A104: 101 | B104: SUPERMARKET LA COLOMBIANA SAS ZOMAC | D104: ADM | E104: =IF(OR(B104="",C104=""),"",IFERROR(VLOOKUP(B104&"|||"&C104,MAESTRA!$A$3:$J$500,6,0),"⚠ No encontrado")) | F104: =IF(OR(B104="",C104=""),"",IFERROR(VLOOKUP(B104&"|||"&C104,MAESTRA!$A$3:$J$500,7,0),"⚠ No encontrado")) | G104: Material Copa/Cozinha | H104: =IF(OR(B104="",C104=""),"",IFERROR(VLOOKUP(B104&"|||"&C104,MAESTRA!$A$3:$J$500,9,0),"")) | I104: NO PAGAR LEGALIZA CAJA MENOR BUENAVENTURA COMPRA BOTELLON DE AGUA | J104: Buenaventura | K104: SMEF54898 | L104: 46107 | N104: 30000 | O104: 23 | P104: 46120 | T104: marzo 2026
A105: 102 | B105: CADENA COMERCIAL OXXO COLOMBIA S A S | D105: ADM | E105: =IF(OR(B105="",C105=""),"",IFERROR(VLOOKUP(B105&"|||"&C105,MAESTRA!$A$3:$J$500,6,0),"⚠ No encontrado")) | F105: =IF(OR(B105="",C105=""),"",IFERROR(VLOOKUP(B105&"|||"&C105,MAESTRA!$A$3:$J$500,7,0),"⚠ No encontrado")) | G105: Reuniones gerenciales CEM (Comida) | H105: =IF(OR(B105="",C105=""),"",IFERROR(VLOOKUP(B105&"|||"&C105,MAESTRA!$A$3:$J$500,9,0),"")) | I105: NO PAGAR LEGALIZA TARJETA PEOPLE PASS GINNA CASTRO COMPRA AGUA REUNION CEM | J105: Calle 100 | K105: 234C232183 | L105: 46105 | N105: 29250 | O105: 7065 | P105: 46120 | R105: APROBACIÓN GERENCIA DE PERSONAS Y ADMÓN | T105: marzo 2026
A106: 103 | B106: AMORE GROUP SAS | D106: ADM | E106: =IF(OR(B106="",C106=""),"",IFERROR(VLOOKUP(B106&"|||"&C106,MAESTRA!$A$3:$J$500,6,0),"⚠ No encontrado")) | F106: =IF(OR(B106="",C106=""),"",IFERROR(VLOOKUP(B106&"|||"&C106,MAESTRA!$A$3:$J$500,7,0),"⚠ No encontrado")) | G106: Gastos De Representacion | H106: =IF(OR(B106="",C106=""),"",IFERROR(VLOOKUP(B106&"|||"&C106,MAESTRA!$A$3:$J$500,9,0),"")) | I106: NO PAGAR LEGALIZA DIANA GRACIA ALMUERZO CON CLIENTE | J106: Cali | K106: 04FA132091 | L106: 46099 | N106: 197100 | O106: 8 | P106: 46120 | T106: marzo 2026
...

Sheet ARCHIVO PLANO NO PAGAR
A1: ARCHIVO PLANO NO PAGAR — PARA CONTABILIDAD | Generado automáticamente desde REGISTRO NO PAGAR
A3: N° | B3: Proveedor | C3: Servicio | D3: Área | E3: P&L | F3: Cuenta Contable | G3: Glosa | H3: Detalle del Gasto | I3: Sucursal | J3: N° Factura | K3: Fecha Realización Eventos | L3: Monto | M3: Mes Ejecución
A4: =IF('REGISTRO NO PAGAR'!B4="","",'REGISTRO NO PAGAR'!A4) | B4: =IF('REGISTRO NO PAGAR'!B4="","",'REGISTRO NO PAGAR'!B4) | C4: =IF('REGISTRO NO PAGAR'!B4="","",'REGISTRO NO PAGAR'!C4) | D4: =IF('REGISTRO NO PAGAR'!B4="","",'REGISTRO NO PAGAR'!D4) | E4: =IF('REGISTRO NO PAGAR'!B4="","",'REGISTRO NO PAGAR'!E4) | F4: =IF('REGISTRO NO PAGAR'!B4="","",'REGISTRO NO PAGAR'!F4) | G4: =IF('REGISTRO NO PAGAR'!B4="","",'REGISTRO NO PAGAR'!G4) | H4: =IF('REGISTRO NO PAGAR'!B4="","",'REGISTRO NO PAGAR'!I4) | I4: =IF('REGISTRO NO PAGAR'!B4="","",'REGISTRO NO PAGAR'!J4) | J4: =IF('REGISTRO NO PAGAR'!B4="","",'REGISTRO NO PAGAR'!K4) | K4: =IF('REGISTRO NO PAGAR'!B4="","",'REGISTRO NO PAGAR'!M4) | L4: =IF('REGISTRO NO PAGAR'!B4="","",'REGISTRO NO PAGAR'!N4) | M4: =IF('REGISTRO NO PAGAR'!B4="","",'REGISTRO NO PAGAR'!T4)
A5: =IF('REGISTRO NO PAGAR'!B5="","",'REGISTRO NO PAGAR'!A5) | B5: =IF('REGISTRO NO PAGAR'!B5="","",'REGISTRO NO PAGAR'!B5) | C5: =IF('REGISTRO NO PAGAR'!B5="","",'REGISTRO NO PAGAR'!C5) | D5: =IF('REGISTRO NO PAGAR'!B5="","",'REGISTRO NO PAGAR'!D5) | E5: =IF('REGISTRO NO PAGAR'!B5="","",'REGISTRO NO PAGAR'!E5) | F5: =IF('REGISTRO NO PAGAR'!B5="","",'REGISTRO NO PAGAR'!F5) | G5: =IF('REGISTRO NO PAGAR'!B5="","",'REGISTRO NO PAGAR'!G5) | H5: =IF('REGISTRO NO PAGAR'!B5="","",'REGISTRO NO PAGAR'!I5) | I5: =IF('REGISTRO NO PAGAR'!B5="","",'REGISTRO NO PAGAR'!J5) | J5: =IF('REGISTRO NO PAGAR'!B5="","",'REGISTRO NO PAGAR'!K5) | K5: =IF('REGISTRO NO PAGAR'!B5="","",'REGISTRO NO PAGAR'!M5) | L5: =IF('REGISTRO NO PAGAR'!B5="","",'REGISTRO NO PAGAR'!N5) | M5: =IF('REGISTRO NO PAGAR'!B5="","",'REGISTRO NO PAGAR'!T5)
A6: =IF('REGISTRO NO PAGAR'!B6="","",'REGISTRO NO PAGAR'!A6) | B6: =IF('REGISTRO NO PAGAR'!B6="","",'REGISTRO NO PAGAR'!B6) | C6: =IF('REGISTRO NO PAGAR'!B6="","",'REGISTRO NO PAGAR'!C6) | D6: =IF('REGISTRO NO PAGAR'!B6="","",'REGISTRO NO PAGAR'!D6) | E6: =IF('REGISTRO NO PAGAR'!B6="","",'REGISTRO NO PAGAR'!E6) | F6: =IF('REGISTRO NO PAGAR'!B6="","",'REGISTRO NO PAGAR'!F6) | G6: =IF('REGISTRO NO PAGAR'!B6="","",'REGISTRO NO PAGAR'!G6) | H6: =IF('REGISTRO NO PAGAR'!B6="","",'REGISTRO NO PAGAR'!I6) | I6: =IF('REGISTRO NO PAGAR'!B6="","",'REGISTRO NO PAGAR'!J6) | J6: =IF('REGISTRO NO PAGAR'!B6="","",'REGISTRO NO PAGAR'!K6) | K6: =IF('REGISTRO NO PAGAR'!B6="","",'REGISTRO NO PAGAR'!M6) | L6: =IF('REGISTRO NO PAGAR'!B6="","",'REGISTRO NO PAGAR'!N6) | M6: =IF('REGISTRO NO PAGAR'!B6="","",'REGISTRO NO PAGAR'!T6)
A7: =IF('REGISTRO NO PAGAR'!B7="","",'REGISTRO NO PAGAR'!A7) | B7: =IF('REGISTRO NO PAGAR'!B7="","",'REGISTRO NO PAGAR'!B7) | C7: =IF('REGISTRO NO PAGAR'!B7="","",'REGISTRO NO PAGAR'!C7) | D7: =IF('REGISTRO NO PAGAR'!B7="","",'REGISTRO NO PAGAR'!D7) | E7: =IF('REGISTRO NO PAGAR'!B7="","",'REGISTRO NO PAGAR'!E7) | F7: =IF('REGISTRO NO PAGAR'!B7="","",'REGISTRO NO PAGAR'!F7) | G7: =IF('REGISTRO NO PAGAR'!B7="","",'REGISTRO NO PAGAR'!G7) | H7: =IF('REGISTRO NO PAGAR'!B7="","",'REGISTRO NO PAGAR'!I7) | I7: =IF('REGISTRO NO PAGAR'!B7="","",'REGISTRO NO PAGAR'!J7) | J7: =IF('REGISTRO NO PAGAR'!B7="","",'REGISTRO NO PAGAR'!K7) | K7: =IF('REGISTRO NO PAGAR'!B7="","",'REGISTRO NO PAGAR'!M7) | L7: =IF('REGISTRO NO PAGAR'!B7="","",'REGISTRO NO PAGAR'!N7) | M7: =IF('REGISTRO NO PAGAR'!B7="","",'REGISTRO NO PAGAR'!T7)
A8: =IF('REGISTRO NO PAGAR'!B8="","",'REGISTRO NO PAGAR'!A8) | B8: =IF('REGISTRO NO PAGAR'!B8="","",'REGISTRO NO PAGAR'!B8) | C8: =IF('REGISTRO NO PAGAR'!B8="","",'REGISTRO NO PAGAR'!C8) | D8: =IF('REGISTRO NO PAGAR'!B8="","",'REGISTRO NO PAGAR'!D8) | E8: =IF('REGISTRO NO PAGAR'!B8="","",'REGISTRO NO PAGAR'!E8) | F8: =IF('REGISTRO NO PAGAR'!B8="","",'REGISTRO NO PAGAR'!F8) | G8: =IF('REGISTRO NO PAGAR'!B8="","",'REGISTRO NO PAGAR'!G8) | H8: =IF('REGISTRO NO PAGAR'!B8="","",'REGISTRO NO PAGAR'!I8) | I8: =IF('REGISTRO NO PAGAR'!B8="","",'REGISTRO NO PAGAR'!J8) | J8: =IF('REGISTRO NO PAGAR'!B8="","",'REGISTRO NO PAGAR'!K8) | K8: =IF('REGISTRO NO PAGAR'!B8="","",'REGISTRO NO PAGAR'!M8) | L8: =IF('REGISTRO NO PAGAR'!B8="","",'REGISTRO NO PAGAR'!N8) | M8: =IF('REGISTRO NO PAGAR'!B8="","",'REGISTRO NO PAGAR'!T8)
A9: =IF('REGISTRO NO PAGAR'!B9="","",'REGISTRO NO PAGAR'!A9) | B9: =IF('REGISTRO NO PAGAR'!B9="","",'REGISTRO NO PAGAR'!B9) | C9: =IF('REGISTRO NO PAGAR'!B9="","",'REGISTRO NO PAGAR'!C9) | D9: =IF('REGISTRO NO PAGAR'!B9="","",'REGISTRO NO PAGAR'!D9) | E9: =IF('REGISTRO NO PAGAR'!B9="","",'REGISTRO NO PAGAR'!E9) | F9: =IF('REGISTRO NO PAGAR'!B9="","",'REGISTRO NO PAGAR'!F9) | G9: =IF('REGISTRO NO PAGAR'!B9="","",'REGISTRO NO PAGAR'!G9) | H9: =IF('REGISTRO NO PAGAR'!B9="","",'REGISTRO NO PAGAR'!I9) | I9: =IF('REGISTRO NO PAGAR'!B9="","",'REGISTRO NO PAGAR'!J9) | J9: =IF('REGISTRO NO PAGAR'!B9="","",'REGISTRO NO PAGAR'!K9) | K9: =IF('REGISTRO NO PAGAR'!B9="","",'REGISTRO NO PAGAR'!M9) | L9: =IF('REGISTRO NO PAGAR'!B9="","",'REGISTRO NO PAGAR'!N9) | M9: =IF('REGISTRO NO PAGAR'!B9="","",'REGISTRO NO PAGAR'!T9)
A10: =IF('REGISTRO NO PAGAR'!B10="","",'REGISTRO NO PAGAR'!A10) | B10: =IF('REGISTRO NO PAGAR'!B10="","",'REGISTRO NO PAGAR'!B10) | C10: =IF('REGISTRO NO PAGAR'!B10="","",'REGISTRO NO PAGAR'!C10) | D10: =IF('REGISTRO NO PAGAR'!B10="","",'REGISTRO NO PAGAR'!D10) | E10: =IF('REGISTRO NO PAGAR'!B10="","",'REGISTRO NO PAGAR'!E10) | F10: =IF('REGISTRO NO PAGAR'!B10="","",'REGISTRO NO PAGAR'!F10) | G10: =IF('REGISTRO NO PAGAR'!B10="","",'REGISTRO NO PAGAR'!G10) | H10: =IF('REGISTRO NO PAGAR'!B10="","",'REGISTRO NO PAGAR'!I10) | I10: =IF('REGISTRO NO PAGAR'!B10="","",'REGISTRO NO PAGAR'!J10) | J10: =IF('REGISTRO NO PAGAR'!B10="","",'REGISTRO NO PAGAR'!K10) | K10: =IF('REGISTRO NO PAGAR'!B10="","",'REGISTRO NO PAGAR'!M10) | L10: =IF('REGISTRO NO PAGAR'!B10="","",'REGISTRO NO PAGAR'!N10) | M10: =IF('REGISTRO NO PAGAR'!B10="","",'REGISTRO NO PAGAR'!T10)
A11: =IF('REGISTRO NO PAGAR'!B11="","",'REGISTRO NO PAGAR'!A11) | B11: =IF('REGISTRO NO PAGAR'!B11="","",'REGISTRO NO PAGAR'!B11) | C11: =IF('REGISTRO NO PAGAR'!B11="","",'REGISTRO NO PAGAR'!C11) | D11: =IF('REGISTRO NO PAGAR'!B11="","",'REGISTRO NO PAGAR'!D11) | E11: =IF('REGISTRO NO PAGAR'!B11="","",'REGISTRO NO PAGAR'!E11) | F11: =IF('REGISTRO NO PAGAR'!B11="","",'REGISTRO NO PAGAR'!F11) | G11: =IF('REGISTRO NO PAGAR'!B11="","",'REGISTRO NO PAGAR'!G11) | H11: =IF('REGISTRO NO PAGAR'!B11="","",'REGISTRO NO PAGAR'!I11) | I11: =IF('REGISTRO NO PAGAR'!B11="","",'REGISTRO NO PAGAR'!J11) | J11: =IF('REGISTRO NO PAGAR'!B11="","",'REGISTRO NO PAGAR'!K11) | K11: =IF('REGISTRO NO PAGAR'!B11="","",'REGISTRO NO PAGAR'!M11) | L11: =IF('REGISTRO NO PAGAR'!B11="","",'REGISTRO NO PAGAR'!N11) | M11: =IF('REGISTRO NO PAGAR'!B11="","",'REGISTRO NO PAGAR'!T11)
A12: =IF('REGISTRO NO PAGAR'!B12="","",'REGISTRO NO PAGAR'!A12) | B12: =IF('REGISTRO NO PAGAR'!B12="","",'REGISTRO NO PAGAR'!B12) | C12: =IF('REGISTRO NO PAGAR'!B12="","",'REGISTRO NO PAGAR'!C12) | D12: =IF('REGISTRO NO PAGAR'!B12="","",'REGISTRO NO PAGAR'!D12) | E12: =IF('REGISTRO NO PAGAR'!B12="","",'REGISTRO NO PAGAR'!E12) | F12: =IF('REGISTRO NO PAGAR'!B12="","",'REGISTRO NO PAGAR'!F12) | G12: =IF('REGISTRO NO PAGAR'!B12="","",'REGISTRO NO PAGAR'!G12) | H12: =IF('REGISTRO NO PAGAR'!B12="","",'REGISTRO NO PAGAR'!I12) | I12: =IF('REGISTRO NO PAGAR'!B12="","",'REGISTRO NO PAGAR'!J12) | J12: =IF('REGISTRO NO PAGAR'!B12="","",'REGISTRO NO PAGAR'!K12) | K12: =IF('REGISTRO NO PAGAR'!B12="","",'REGISTRO NO PAGAR'!M12) | L12: =IF('REGISTRO NO PAGAR'!B12="","",'REGISTRO NO PAGAR'!N12) | M12: =IF('REGISTRO NO PAGAR'!B12="","",'REGISTRO NO PAGAR'!T12)
A13: =IF('REGISTRO NO PAGAR'!B13="","",'REGISTRO NO PAGAR'!A13) | B13: =IF('REGISTRO NO PAGAR'!B13="","",'REGISTRO NO PAGAR'!B13) | C13: =IF('REGISTRO NO PAGAR'!B13="","",'REGISTRO NO PAGAR'!C13) | D13: =IF('REGISTRO NO PAGAR'!B13="","",'REGISTRO NO PAGAR'!D13) | E13: =IF('REGISTRO NO PAGAR'!B13="","",'REGISTRO NO PAGAR'!E13) | F13: =IF('REGISTRO NO PAGAR'!B13="","",'REGISTRO NO PAGAR'!F13) | G13: =IF('REGISTRO NO PAGAR'!B13="","",'REGISTRO NO PAGAR'!G13) | H13: =IF('REGISTRO NO PAGAR'!B13="","",'REGISTRO NO PAGAR'!I13) | I13: =IF('REGISTRO NO PAGAR'!B13="","",'REGISTRO NO PAGAR'!J13) | J13: =IF('REGISTRO NO PAGAR'!B13="","",'REGISTRO NO PAGAR'!K13) | K13: =IF('REGISTRO NO PAGAR'!B13="","",'REGISTRO NO PAGAR'!M13) | L13: =IF('REGISTRO NO PAGAR'!B13="","",'REGISTRO NO PAGAR'!N13) | M13: =IF('REGISTRO NO PAGAR'!B13="","",'REGISTRO NO PAGAR'!T13)
A14: =IF('REGISTRO NO PAGAR'!B14="","",'REGISTRO NO PAGAR'!A14) | B14: =IF('REGISTRO NO PAGAR'!B14="","",'REGISTRO NO PAGAR'!B14) | C14: =IF('REGISTRO NO PAGAR'!B14="","",'REGISTRO NO PAGAR'!C14) | D14: =IF('REGISTRO NO PAGAR'!B14="","",'REGISTRO NO PAGAR'!D14) | E14: =IF('REGISTRO NO PAGAR'!B14="","",'REGISTRO NO PAGAR'!E14) | F14: =IF('REGISTRO NO PAGAR'!B14="","",'REGISTRO NO PAGAR'!F14) | G14: =IF('REGISTRO NO PAGAR'!B14="","",'REGISTRO NO PAGAR'!G14) | H14: =IF('REGISTRO NO PAGAR'!B14="","",'REGISTRO NO PAGAR'!I14) | I14: =IF('REGISTRO NO PAGAR'!B14="","",'REGISTRO NO PAGAR'!J14) | J14: =IF('REGISTRO NO PAGAR'!B14="","",'REGISTRO NO PAGAR'!K14) | K14: =IF('REGISTRO NO PAGAR'!B14="","",'REGISTRO NO PAGAR'!M14) | L14: =IF('REGISTRO NO PAGAR'!B14="","",'REGISTRO NO PAGAR'!N14) | M14: =IF('REGISTRO NO PAGAR'!B14="","",'REGISTRO NO PAGAR'!T14)
A15: =IF('REGISTRO NO PAGAR'!B15="","",'REGISTRO NO PAGAR'!A15) | B15: =IF('REGISTRO NO PAGAR'!B15="","",'REGISTRO NO PAGAR'!B15) | C15: =IF('REGISTRO NO PAGAR'!B15="","",'REGISTRO NO PAGAR'!C15) | D15: =IF('REGISTRO NO PAGAR'!B15="","",'REGISTRO NO PAGAR'!D15) | E15: =IF('REGISTRO NO PAGAR'!B15="","",'REGISTRO NO PAGAR'!E15) | F15: =IF('REGISTRO NO PAGAR'!B15="","",'REGISTRO NO PAGAR'!F15) | G15: =IF('REGISTRO NO PAGAR'!B15="","",'REGISTRO NO PAGAR'!G15) | H15: =IF('REGISTRO NO PAGAR'!B15="","",'REGISTRO NO PAGAR'!I15) | I15: =IF('REGISTRO NO PAGAR'!B15="","",'REGISTRO NO PAGAR'!J15) | J15: =IF('REGISTRO NO PAGAR'!B15="","",'REGISTRO NO PAGAR'!K15) | K15: =IF('REGISTRO NO PAGAR'!B15="","",'REGISTRO NO PAGAR'!M15) | L15: =IF('REGISTRO NO PAGAR'!B15="","",'REGISTRO NO PAGAR'!N15) | M15: =IF('REGISTRO NO PAGAR'!B15="","",'REGISTRO NO PAGAR'!T15)
... A254: =IF('REGISTRO NO PAGAR'!B254="","",'REGISTRO NO PAGAR'!A254) | B254: =IF('REGISTRO NO PAGAR'!B254="","",'REGISTRO NO PAGAR'!B254) | C254: =IF('REGISTRO NO PAGAR'!B254="","",'REGISTRO NO PAGAR'!C254) | D254: =IF('REGISTRO NO PAGAR'!B254="","",'REGISTRO NO PAGAR'!D254) | E254: =IF('REGISTRO NO PAGAR'!B254="","",'REGISTRO NO PAGAR'!E254) | F254: =IF('REGISTRO NO PAGAR'!B254="","",'REGISTRO NO PAGAR'!F254) | G254: =IF('REGISTRO NO PAGAR'!B254="","",'REGISTRO NO PAGAR'!G254) | H254: =IF('REGISTRO NO PAGAR'!B254="","",'REGISTRO NO PAGAR'!I254) | I254: =IF('REGISTRO NO PAGAR'!B254="","",'REGISTRO NO PAGAR'!J254) | J254: =IF('REGISTRO NO PAGAR'!B254="","",'REGISTRO NO PAGAR'!K254) | K254: =IF('REGISTRO NO PAGAR'!B254="","",'REGISTRO NO PAGAR'!M254) | L254: =IF('REGISTRO NO PAGAR'!B254="","",'REGISTRO NO PAGAR'!N254) | M254: =IF('REGISTRO NO PAGAR'!B254="","",'REGISTRO NO PAGAR'!T254)
